Workbook

Sheet Dashboard
S2: Overall retention rate | T2: ='Pivot Analysis'!F41 -> 1
S3: Retention rate | T3: ='Pivot Analysis'!F41 -> 1
S4: Cohort 1 | T4: ='Pivot Analysis'!F30 -> 0.86956522
S5: Cohort 2 | T5: ='Pivot Analysis'!F31 -> 0.8
S6: Cohort 3 | T6: ='Pivot Analysis'!F32 -> 0.91304348
S7: Cohort 4 | T7: ='Pivot Analysis'!F33 -> 0.96296296
S8: Cohort 5 | T8: ='Pivot Analysis'!F34 -> 0.8
S9: Cohort 6 | T9: ='Pivot Analysis'!F35 -> 0.96
S10: Cohort 7 | T10: ='Pivot Analysis'!F36 -> 0.88888889
S11: Cohort 8 | T11: ='Pivot Analysis'!F37 -> 0.88461538
S12: Cohort 9 | T12: ='Pivot Analysis'!F38 -> 0.91666667
S13: Cohort 10 | T13: ='Pivot Analysis'!F39 -> 0.96
B41: Distribution active fellows by Cohort
B42: Count of Unique ID | C42: Current PhD Status ( Completed/Defended/In Progress)
B43: Cohort | C43: Completed | D43: In progress | E43: Terminated | F43: Grand Total | G43: Retention rate | S43: =2 -> 2
B44: 1 | C44: 20 | E44: 3 | F44: 23
B45: 2 | C45: 15 | D45: 1 | E45: 4 | F45: 20
B46: 3 | C46: 18 | D46: 3 | E46: 2 | F46: 23
B47: 4 | C47: 25 | D47: 1 | E47: 1 | F47: 27
B48: 5 | C48: 18 | D48: 2 | E48: 5 | F48: 25
B49: 6 | C49: 24 | E49: 1 | F49: 25
B50: 7 | C50: 24 | E50: 3 | F50: 27 | H50: -
B51: 8 | C51: 17 | D51: 6 | E51: 3 | F51: 26
B52: 9 | C52: 16 | D52: 6 | E52: 2 | F52: 24
B53: 10 | C53: 20 | D53: 4 | E53: 1 | F53: 25
B54: 11 | D54: 19 | E54: 1 | F54: 20
B55: 12 | D55: 22 | F55: 22
B56: Grand Total | C56: 197 | D56: 64 | E56: 26 | F56: 287

Sheet Sheet2
A3: Count of S.No. | B3: Column Labels
A4: Row Labels | B4: Completed | C4: In progress | D4: Terminated | E4: Grand Total
A5: 1 | B5: 20 | D5: 3 | E5: 23
A6: 2 | B6: 15 | C6: 1 | D6: 4 | E6: 20
A7: 3 | B7: 18 | C7: 3 | D7: 2 | E7: 23
A8: 4 | B8: 25 | C8: 1 | D8: 1 | E8: 27
A9: 5 | B9: 18 | C9: 2 | D9: 5 | E9: 25
A10: 6 | B10: 24 | D10: 1 | E10: 25
A11: 7 | B11: 24 | D11: 3 | E11: 27
A12: 8 | B12: 17 | C12: 6 | D12: 3 | E12: 26
A13: 9 | B13: 16 | C13: 6 | D13: 2 | E13: 24
A14: 10 | B14: 20 | C14: 4 | D14: 1 | E14: 25
A15: Grand Total | B15: 197 | C15: 23 | D15: 25 | E15: 245
A20: Count of S.No. | B20: Column Labels
A21: Row Labels | B21: Completed | C21: In progress | D21: Terminated | E21: Grand Total
A22: Man | B22: 86 | C22: 10 | D22: 13 | E22: 109
A23: Woman | B23: 111 | C23: 13 | D23: 12 | E23: 136
A24: Grand Total | B24: 197 | C24: 23 | D24: 25 | E24: 245
C33: =65+78+32+49+12+9 -> 245
B34: Row Labels | C34: Female | D34: Male | E34: Grand Total
B35: Completed | C35: 80 | D35: 65 | E35: 145
B36: In progress | C36: 47 | D36: 32 | E36: 79
B37: Terminated | C37: 9 | D37: 12 | E37: 21
B38: Grand Total | C38: 136 | D38: 109 | E38: 245

Sheet Pivot Analysis
A1: Active fellows by institution of registration | H1: Active fellows by institution of employment | S1: Cohort | T1: Male | U1: Female | V1: Total
A2: Gender | B2: (All) | H2: Gender | I2: (All) | N2: Current PhD Status ( Completed/Defended/In Progress) | O2: (All) | P2: Current PhD Status ( Completed/Defended/In Progress) | Q2: Completed | S2: University of Ibadan
N3: Distribution active fellows by Cohort | P3: Distribution active fellows by Cohort
A4: Count of Unique ID | B4: Current PhD Status ( Completed/Defended/In Progress) | H4: Count of Unique ID | I4: Current PhD Status ( Completed/Defended/In Progress) | N4: Gender | O4: Count of Unique ID | P4: Gender | Q4: Count of Unique ID
A5: Institution of registration | B5: Completed | C5: In progress | D5: Terminated | E5: (blank) | F5: Grand Total | H5: Institution of employment at registration | I5: Completed | J5: In progress | K5: Terminated | L5: Grand Total | N5: Man | O5: 130 | P5: Man | Q5: 86
A6: Makerere University | B6: 17 | C6: 9 | D6: 3 | F6: 29 | H6: AGINCOURT | I6: 1 | J6: 2 | L6: 3 | N6: Woman | O6: 157 | P6: Woman | Q6: 111
A7: Moi University | B7: 7 | C7: 6 | F7: 13 | H7: APHRC | I7: 4 | J7: 1 | K7: 1 | L7: 6 | N7: Grand Total | O7: 287 | P7: Grand Total | Q7: 197
A8: Obafemi Awolowo University | B8: 19 | C8: 1 | F8: 20 | H8: Ifakara Health Institute | I8: 7 | J8: 2 | K8: 1 | L8: 10
A9: University of Dar es Salaam | B9: 6 | D9: 2 | F9: 8 | H9: Makerere University | I9: 19 | J9: 8 | K9: 4 | L9: 31
A10: University of Ibadan | B10: 29 | C10: 10 | F10: 39 | H10: Moi University | I10: 13 | J10: 8 | K10: 1 | L10: 22
A11: University of Nairobi | B11: 22 | C11: 10 | D11: 5 | F11: 37 | H11: Obafemi Awolowo University | I11: 30 | J11: 3 | L11: 33
A12: University of Rwanda | B12: 6 | C12: 7 | F12: 13 | H12: University of Dar es Salaam | I12: 4 | K12: 2 | L12: 6
A13: University of the Witwatersrand | B13: 75 | C13: 14 | D13: 8 | F13: 97 | H13: University of Ibadan | I13: 32 | J13: 11 | L13: 43 | O13: Count of Unique ID | P13: Gender
A14: (blank) | C14: 1 | D14: 5 | F14: 6 | H14: University of Nairobi | I14: 17 | J14: 7 | K14: 7 | L14: 31 | O14: Cohort | P14: Man | Q14: Woman | R14: Grand Total
A15: University of Malawi and Associates | B15: 16 | C15: 6 | D15: 3 | F15: 25 | H15: University of Rwanda | I15: 20 | J15: 9 | K15: 2 | L15: 31 | O15: 1 | P15: 14 | Q15: 9 | R15: 23
A16: Grand Total | B16: 197 | C16: 64 | D16: 26 | F16: 287 | H16: University of the Witwatersrand | I16: 25 | J16: 2 | K16: 5 | L16: 32 | O16: 2 | P16: 11 | Q16: 9 | R16: 20
H17: Somali National University | J17: 2 | L17: 2 | O17: 3 | P17: 10 | Q17: 13 | R17: 23
H18: University of Malawi and Associates | I18: 25 | J18: 9 | K18: 3 | L18: 37 | O18: 4 | P18: 15 | Q18: 12 | R18: 27
H19: Grand Total | I19: 197 | J19: 64 | K19: 26 | L19: 287 | O19: 5 | P19: 12 | Q19: 13 | R19: 25
O20: 6 | P20: 10 | Q20: 15 | R20: 25
O21: 7 | P21: 8 | Q21: 19 | R21: 27
O22: 8 | P22: 10 | Q22: 16 | R22: 26
O23: 9 | P23: 9 | Q23: 15 | R23: 24
O24: 10 | P24: 10 | Q24: 15 | R24: 25
O25: 11 | P25: 9 | Q25: 11 | R25: 20
O26: 12 | P26: 12 | Q26: 10 | R26: 22
A27: Distribution active fellows by Cohort | H27: Current PhD Status ( Completed/Defended/In Progress) | I27: (All) | O27: Grand Total | P27: 130 | Q27: 157 | R27: 287
A28: Count of Unique ID | B28: Current PhD Status ( Completed/Defended/In Progress)
A29: Cohort | B29: Completed | C29: In progress | D29: Terminated | E29: Grand Total | F29: Retention Rate | H29: Count of Unique ID | I29: Gender
A30: 1 | B30: 20 | D30: 3 | E30: 23 | F30: =SUM(B30:C30)/E30 -> 0.86956522 | H30: Nationality | I30: Man | J30: Woman | K30: Grand Total | N30: Cohort 1-10 Demographics.xlsx]Fellows!A1:CJ266
A31: 2 | B31: 15 | C31: 1 | D31: 4 | E31: 20 | F31: =SUM(B31:C31)/E31 -> 0.8 | H31: Kenya | I31: 16 | J31: 42 | K31: 58
A32: 3 | B32: 18 | C32: 3 | D32: 2 | E32: 23 | F32: =SUM(B32:C32)/E32 -> 0.91304348 | H32: Malawi | I32: 24 | J32: 15 | K32: 39
A33: 4 | B33: 25 | C33: 1 | D33: 1 | E33: 27 | F33: =SUM(B33:C33)/E33 -> 0.96296296 | H33: Nigeria | I33: 36 | J33: 42 | K33: 78
A34: 5 | B34: 18 | C34: 2 | D34: 5 | E34: 25 | F34: =SUM(B34:C34)/E34 -> 0.8 | H34: Rwanda | I34: 19 | J34: 12 | K34: 31
A35: 6 | B35: 24 | D35: 1 | E35: 25 | F35: =SUM(B35:C35)/E35 -> 0.96 | H35: Senegal | I35: 1 | K35: 1
A36: 7 | B36: 24 | D36: 3 | E36: 27 | F36: =SUM(B36:C36)/E36 -> 0.88888889 | H36: Somalia | I36: 1 | J36: 1 | K36: 2
A37: 8 | B37: 17 | C37: 6 | D37: 3 | E37: 26 | F37: =SUM(B37:C37)/E37 -> 0.88461538 | H37: South Africa | I37: 8 | J37: 20 | K37: 28
A38: 9 | B38: 16 | C38: 6 | D38: 2 | E38: 24 | F38: =SUM(B38:C38)/E38 -> 0.91666667 | H38: Tanzania | I38: 7 | J38: 9 | K38: 16
A39: 10 | B39: 20 | C39: 4 | D39: 1 | E39: 25 | F39: =SUM(B39:C39)/E39 -> 0.96 | H39: Uganda | I39: 17 | J39: 14 | K39: 31
A40: 11 | C40: 19 | D40: 1 | E40: 20 | F40: =SUM(B40:C40)/E40 -> 0.95 | H40: Zimbabwe | I40: 1 | J40: 2 | K40: 3
A41: 12 | C41: 22 | E41: 22 | F41: =SUM(B41:C41)/E41 -> 1 | H41: Grand Total | I41: 130 | J41: 157 | K41: 287
A42: Grand Total | B42: 197 | C42: 64 | D42: 26 | E42: 287
P57: =109/245 -> 0.44489796
P58: =136/245 -> 0.55510204
A62: Current PhD Status ( Completed/Defended/In Progress) | B62: (All)
A64: Count of Unique ID | B64: Gender
A65: Cohort | B65: Man | C65: Woman | D65: Grand Total | H65: Cohort
A66: 1 | B66: 14 | C66: 9 | D66: 23 | H66: Count of Unique ID | I66: Current PhD Status ( Completed/Defended/In Progress)
A67: 2 | B67: 11 | C67: 9 | D67: 20 | H67: Cohort | I67: Completed | J67: In progress | K67: Terminated | L67: Grand Total
A68: 3 | B68: 10 | C68: 13 | D68: 23 | H68: 1 | I68: 20 | K68: 3 | L68: 23
A69: 4 | B69: 15 | C69: 12 | D69: 27 | H69: 2 | I69: 15 | J69: 1 | K69: 4 | L69: 20
A70: 5 | B70: 12 | C70: 13 | D70: 25 | H70: 3 | I70: 18 | J70: 3 | K70: 2 | L70: 23
A71: 6 | B71: 10 | C71: 15 | D71: 25 | H71: 4 | I71: 25 | J71: 1 | K71: 1 | L71: 27
A72: 7 | B72: 8 | C72: 19 | D72: 27 | H72: 5 | I72: 18 | J72: 2 | K72: 5 | L72: 25
A73: 8 | B73: 10 | C73: 16 | D73: 26 | H73: 6 | I73: 24 | K73: 1 | L73: 25
A74: 9 | B74: 9 | C74: 15 | D74: 24 | H74: 7 | I74: 24 | K74: 3 | L74: 27
A75: 10 | B75: 10 | C75: 15 | D75: 25 | H75: 8 | I75: 17 | J75: 6 | K75: 3 | L75: 26
A76: 11 | B76: 9 | C76: 11 | D76: 20 | H76: 9 | I76: 16 | J76: 6 | K76: 2 | L76: 24
A77: 12 | B77: 12 | C77: 10 | D77: 22 | H77: 10 | I77: 20 | J77: 4 | K77: 1 | L77: 25
A78: Grand Total | B78: 130 | C78: 157 | D78: 287 | H78: 11 | J78: 19 | K78: 1 | L78: 20
H79: 12 | J79: 22 | L79: 22
H80: Grand Total | I80: 197 | J80: 64 | K80: 26 | L80: 287
A90: Count of S.No. | B90: Column Labels
A91: Row Labels | B91: Completed | C91: In progress | D91: Terminated | E91: Grand Total
A92: Man | B92: 86 | C92: 10 | D92: 13 | E92: 109
A93: Woman | B93: 111 | C93: 13 | D93: 12 | E93: 136 | H93: Count of Unique ID | I93: Gender
A94: Grand Total | B94: 197 | C94: 23 | D94: 25 | E94: 245 | H94: Institution of employment at registration | I94: Man | J94: Woman | K94: Grand Total
H95: AGINCOURT | I95: 3 | K95: 3
H96: APHRC | I96: 5 | J96: 1 | K96: 6
H97: Ifakara Health Institute | I97: 4 | J97: 6 | K97: 10
H98: Makerere University | I98: 17 | J98: 14 | K98: 31
H99: Moi University | I99: 5 | J99: 17 | K99: 22
A100: Count of Unique ID | B100: Current PhD Status ( Completed/Defended/In Progress) | H100: Obafemi Awolowo University | I100: 15 | J100: 18 | K100: 33
A101: Institution of employment at registration | B101: Completed | C101: In progress | D101: Terminated | E101: Grand Total | H101: University of Dar es Salaam | I101: 3 | J101: 3 | K101: 6
A102: AGINCOURT | B102: 1 | C102: 2 | E102: 3 | H102: University of Ibadan | I102: 20 | J102: 23 | K102: 43
A103: APHRC | B103: 4 | C103: 1 | D103: 1 | E103: 6 | H103: University of Nairobi | I103: 7 | J103: 24 | K103: 31
A104: Ifakara Health Institute | B104: 7 | C104: 2 | D104: 1 | E104: 10 | H104: University of Rwanda | I104: 19 | J104: 12 | K104: 31
A105: Makerere University | B105: 19 | C105: 8 | D105: 4 | E105: 31 | H105: University of the Witwatersrand | I105: 9 | J105: 23 | K105: 32
A106: Moi University | B106: 13 | C106: 8 | D106: 1 | E106: 22 | H106: Somali National University | I106: 1 | J106: 1 | K106: 2
A107: Obafemi Awolowo University | B107: 30 | C107: 3 | E107: 33 | H107: University of Malawi and Associates | I107: 22 | J107: 15 | K107: 37
A108: University of Dar es Salaam | B108: 4 | D108: 2 | E108: 6 | H108: Grand Total | I108: 130 | J108: 157 | K108: 287
A109: University of Ibadan | B109: 32 | C109: 11 | E109: 43
A110: University of Nairobi | B110: 17 | C110: 7 | D110: 7 | E110: 31
A111: University of Rwanda | B111: 20 | C111: 9 | D111: 2 | E111: 31
A112: University of the Witwatersrand | B112: 25 | C112: 2 | D112: 5 | E112: 32
A113: Somali National University | C113: 2 | E113: 2
A114: University of Malawi and Associates | B114: 25 | C114: 9 | D114: 3 | E114: 37
A115: Grand Total | B115: 197 | C115: 64 | D115: 26 | E115: 287

Sheet Fellows
A1: S.No. | B1: Unique ID | C1: First Name | D1: Middle Name | E1: Surname | F1: Gender | G1: Cohort | H1: Nationality | I1: Institution of employment at registration | J1: Discipline | K1: Department | L1: Institution of registration | M1: Registered at Home | N1: PhD Student Number at Host Institution | O1: Marital Status at enrolment | P1: Current Marital Status | Q1: Marital Status at Completion | R1: Email | S1: Alternative e-mail | T1: Phone | U1: Masters Degree | V1: DOB | W1: Proposed Research Title | X1: Type of study | Y1: Laboratory work? | Z1: Type of data | AA1: Ranking | AB1: Date of PhD registration | AC1: Year of admission into CARTA | AD1: Terminated | AE1: 1st Supervisors | AF1: 2nd Supervisor | AG1: 3rd Supervisor | AH1: Number of supervisors | AI1: Institution for 1st Supervisor | AJ1: Institution for 2nd Supervisor | AK1: Institution for 3rd Supervisor | AL1: 1st Supervisors workshop Attendance | AM1: 2nd Supervisors workshop Attendance | AN1: 3rd Supervisors workshop Attendance | AO1: Type of employment | AP1: Position at Enrollment | AQ1: Current Position | AR1: Promotion event | AS1: Other responsibilities | AT1: Current Institution (Year of change in ()) | AU1: ORCID | AV1: Suspensions | AW1: Month/ Year JAS1 | AX1: Month/ Year JAS2 | AY1: Attended JAS 2 on time | AZ1: Date of protocol submission to PG | BA1: Date of protocol submission to IRB | BB1: Date of Ethics approval | BC1: Review body | BD1: Ethiical reference number | BE1: Approcved research topic | BF1: Month/ Year JAS3 | BG1: Attended JAS 3 on time | BH1: Month/ Year JAS4 | BI1: Attended JAS 4 on time | BJ1: Date of submission of dissertation for examination | BK1: Date of defense | BL1: Date of submission of corrections | BM1: Date of completion(Defended/Graduated) | BN1: Current PhD Status ( Completed/Defended/In Progress) | BO1: Time to completion since enrolling CARTA (Months) | BP1: Time to completion since PhD registration (Months) | BQ1: Thesis title | BR1: No of Publications at Enrollment | BS1: No of Publications During PhD | BT1: No of Publications after PhD | BU1: 1st Author PhD Publications | BV1: Last Author PhD Publications | BW1: 1st Author Graduate Publications | BX1: Last Author Graduate Publications | BY1: Baby Minder (Event, Year) | BZ1: Taken on leave of absence (Yes/No) | CA1: Reason for taking leave of absence | CB1: Leave start Date | CC1: Leave end Date | CD1: Time taken on leave (months) | CE1: Teacher Replacement | CF1: Teacher replacement start Date | CG1: Teacher replacement end Date | CH1: No. of Children at Entry in CARTA | CI1: No. of children at graduation | CJ1: No of Publications for Graduation | CK1: Fellow Funder
A2: 1 | B2: C1/001 | C2: Babatunde | D2: Olubayo | E2: Adedokun | F2: Man | G2: 1 | H2: Nigeria | I2: University of Ibadan | J2: Epidemiology & Medical Biostatistics | K2: Epidemiology and Medical Statistics | L2: University of Ibadan | M2: Yes | O2: Married | P2: Married | Q2: Married | R2: badedokun@cartafrica.org | S2: tukankar@yahoo.co.uk | U2: M.Sc Epidemiology & Medical Statistics | V2: 28116 | W2: Joint modelling of CD4 counts and time to loss to follow up among HIV patients attending antiretroviral clinics in Nigeria | X2: Clinical research | Y2: yes | Z2: Primary | AA2: 16.5 | AB2: 40603 | AC2: 40603 | AE2: Prof Afolabi Bamgboye | AF2: Prof. Olusola Ayeni | AH2: =COUNTA(AE2:AG2) -> 2 | AI2: Home | AJ2: Host | AL2: Yes | AM2: No | AO2: Academic | AQ2: Lecturer | AR2: Yes | AT2: UNIVERSITY OF CHICAGO, UNITED STATES | AU2: 0000-0002-6893-6468 | AW2: 40634 | AX2: 40878 | AY2: Yes | BF2: 41456 | BG2: Yes | BH2: 41699 | BI2: Yes | BM2: 42766 | BN2: Completed | BO2: =DATEDIF(AW2,BM2, "M")+1 -> 70 | BP2: =DATEDIF(AX2,BM2, "M")+1 -> 62 | BR2: 20 | BS2: 29 | BT2: 26 | BU2: 2 | BV2: 3 | BW2: 0 | BX2: 0 | BY2: No | BZ2: No | CE2: No | CH2: 0 | CI2: 1 | CK2: NF
A3: 2 | B3: C1/002 | C3: Celine | E3: Niwemahoro | F3: Woman | G3: 1 | H3: Rwanda | I3: University of Rwanda | J3: Demography & Population Studies | K3: Applied Statistics | L3: University of Dar es Salaam | M3: No | O3: Married | P3: Married | R3: cniwemahoro@cartafrica.org | S3: ncmahoro2000@yahoo.fr | T3: +250788350522/254723489604 | U3: Masters in Demography and Population Studies (online) | V3: 29416 | W3: Premarital Fertility and Use Of Health Care: Effect On HIV And Prevention Mother-To-Child Transmission (PMTCT) In Rwanda | X3: Field | Y3: No | Z3: Primary | AA3: 26 | AB3: 40616 | AC3: 40603 | AE3: Dr. Julius Kivelia | AH3: =COUNTA(AE3:AG3) -> 1 | AI3: Host | AL3: Yes | AO3: Academic | AP3: Assistant Lecturer | AQ3: Researcher | AR3: Yes | AT3: SCUB - CONSULTANCY FIRM NAIROBI | AU3: 0000-0003-2008-3061 | AW3: 40637 | AX3: 40878 | AY3: Yes | AZ3: 41186 | BB3: 41473 | BE3: Premarital pregnancies and experiences in antenatal care health seeking behavior in Huye District, Rwanda | BF3: 41458 | BG3: Yes | BH3: 41700 | BI3: Yes | BJ3: 42986 | BK3: 43006 | BL3: 43023 | BM3: 43023 | BN3: Completed | BO3: =DATEDIF(AW3,BM3, "M")+1 -> 79 | BP3: =DATEDIF(AX3,BM3, "M")+1 -> 71 | BQ3: Premarital pregnancies and experiences in antenatal care health seeking behavior in Huye District, Rwanda | BR3: 0 | BS3: 0 | BT3: 0 | BU3: 0 | BV3: 0 | BW3: 0 | BX3: 0 | BY3: No | BZ3: No | CE3: No | CH3: 2 | CI3: 2 | CJ3: 0 | CK3: NF
A4: 3 | B4: C1/003 | C4: Caroline | D4: Sultan | E4: Sambai | F4: Woman | G4: 1 | H4: Kenya | I4: Moi University | J4: Literature | K4: LITERATURE THEATRE AND FILM STUDIES | L4: Moi University | M4: Yes | N4: SASS/DPHIL/LIT/07/11 | P4: Married | R4: csambai@cartafrica.org | S4: carolsambai11@gmail.com | T4: +254722433561 | U4: MA in Africa Literature | V4: 29767 | W4: Television Drama as in Kenya and the Framing of Issues of HIV/AIDS and sexuality | X4: Field | Y4: No | Z4: Primary | AA4: 2.5 | AB4: 40827 | AC4: 40603 | AE4: Prof Christopher Joseph Odhiambo | AF4: Prof. Peter Tirop Simatei | AG4: Caroline Kabiru | AH4: =COUNTA(AE4:AG4) -> 3 | AI4: Home | AJ4: Host | AK4: Other | AL4: Yes | AM4: No | AN4: Yes | AO4: Academic | AP4: Lecturer | AQ4: Lecturer | AR4: Yes | AT4: MOI UNIVERSITY | AU4: 0000-0002-5122-3621 | AW4: 40634 | AX4: 40878 | AY4: Yes | BF4: 41456 | BG4: Yes | BH4: 41701 | BI4: Yes | BM4: 41729 | BN4: Completed | BO4: =DATEDIF(AW4,BM4, "M")+1 -> 36 | BP4: =DATEDIF(AX4,BM4, "M")+1 -> 28 | BR4: 0 | BS4: 1 | BT4: 1 | BU4: 2 | BV4: 0 | BW4: 0 | BX4: 0 | BY4: JAS 2, 2011 | BZ4: No | CE4: No | CH4: NF | CI4: NF | CK4: NF
A5: 4 | B5: C1/004 | C5: Dieudonne | E5: Uwizeye | F5: Man | G5: 1 | H5: Rwanda | I5: University of Rwanda | J5: Demography & Population Studies | K5: Sustainable Development | L5: University of Dar es Salaam | M5: No | O5: Married | P5: Married | Q5: Married | R5: duwizeye@cartafrica.org | S5: dr.uwizeye@gmail.com | T5: (+250) 0788 457 397 | U5: MA English and MA in Development Studies | V5: 29587 | W5: Review Of Environmental And Population Health Challenges In The Rwandan Towns And Innovative Mitigation Strategies For Improved And Sustainble life | X5: Field | Y5: No | Z5: Primary | AA5: 24 | AB5: 40695 | AC5: 40603 | AE5: Dr. Sokoni Cosmas Hassan | AH5: =COUNTA(AE5:AG5) -> 1 | AI5: Host | AJ5: Other | AL5: Yes | AM5: Yes | AO5: Academic | AP5: Assistant Lecturer | AQ5: Associate Professor | AR5: Yes | AS5: Head of Department Deputy Team Leader of a Research Subprogram in Peace, Conflict and Security Studies at the Center for Conflict Management, University of Rwanda. | AT5: UNIVERSITY OF RWANDA | AU5: 0000-0002-9733-8969 | AW5: 40634 | AX5: 40878 | AY5: Yes | BF5: 41456 | BG5: Yes | BH5: 41702 | BI5: Yes | BM5: 42338 | BN5: Completed | BO5: =DATEDIF(AW5,BM5, "M")+1 -> 56 | BP5: =DATEDIF(AX5,BM5, "M")+1 -> 48 | BR5: 0 | BS5: 2 | BT5: 7 | BU5: 2 | BV5: 0 | BW5: 0 | BX5: 0 | BY5: No | BZ5: No | CE5: Yes | CH5: 1 | CI5: 3 | CK5: NF
A6: 5 | B6: C1/005 | C6: Wells | E6: Utembe | F6: Man | G6: 1 | H6: Malawi | I6: University of Malawi and Associates | J6: Environmental Sciences | K6: Physics and Biochemical Sciences | L6: University of the Witwatersrand | M6: No | O6: Married | P6: Married | Q6: Married | R6: wutembe@cartafrica.org | S6: wutembe@poly.ac.mw | U6: Msc Environemntal (online) | V6: 26178 | W6: Assessment of occurrence, profile, distribution and exposure to polycyclic aromatic hydrocarbons (PAHs) in Malawi | X6: Clinical research | Y6: yes | Z6: Primary | AA6: 21 | AB6: 40646 | AC6: 40603 | AE6: Prof Mary Gulumian | AF6: Dr. Louisa Alfazema | AH6: =COUNTA(AE6:AG6) -> 2 | AI6: Host | AJ6: Home | AL6: Yes | AM6: No | AO6: Academic | AP6: Lecturer | AQ6: Senior Medical Epidemiologist | AR6: Yes | AT6: NATIONAL INSTITUTE FOR OCCUPATIONAL HEALTH, SOUTH AFRICA (2012) | AU6: 0000-0001-6547-7692 | AW6: 40634 | AX6: 40878 | AY6: Yes | BF6: 41456 | BG6: Yes | BH6: 42064 | BI6: No | BM6: 42551 | BN6: Completed | BO6: =DATEDIF(AW6,BM6, "M")+1 -> 63 | BP6: =DATEDIF(AX6,BM6, "M")+1 -> 55 | BR6: 0 | BS6: 5 | BT6: 15 | BU6: 4 | BV6: 0 | BW6: 0 | BX6: 0 | BY6: No | BZ6: No | CE6: No | CH6: NF | CI6: NF | CK6: NF
A7: 6 | B7: C1/006 | C7: Victoria | D7: Mathew | E7: Mwakalinga Chuma | F7: Woman | G7: 1 | H7: Tanzania | I7: Ifakara Health Institute | J7: Biomedical and environmental sciences | L7: University of the Witwatersrand | M7: No | O7: Married | P7: married | Q7: Married | R7: vmwakalinga@cartafrica.org | S7: vmwakalinga@ihi.or.tz | T7: +255 738 357315; +255 767 366 539 | U7: Msc Urban Planing and Management | V7: 28383 | W7: Integrated geographical tools can enable targeted urban planning interventions to control malaria and lymphatic filariasis | X7: Field | Y7: No | Z7: Primary | AA7: 16 | AB7: 40609 | AC7: 40603 | AE7: Dr. Maureen Coetzee | AF7: Dr. Gerry Killeen | AG7: Dr. Stefan Dongus | AH7: =COUNTA(AE7:AG7) -> 3 | AI7: Host | AJ7: Home | AK7: Home | AL7: Yes | AM7: Yes | AN7: No | AO7: Researcher | AP7: Assistant lecturer | AQ7: Senior Lecturer | AR7: Yes | AT7: ARTHI UNIVERSITY | AW7: 40634 | AX7: 40878 | AY7: Yes | BF7: 41456 | BG7: Yes | BH7: 41699 | BI7: Yes | BM7: 43073 | BN7: Completed | BO7: =DATEDIF(AW7,BM7, "M")+1 -> 81 | BP7: =DATEDIF(AX7,BM7, "M")+1 -> 73 | BR7: NF | BS7: 4 | BT7: 1 | BU7: 0 | BV7: 0 | BW7: 0 | BX7: 1 | BY7: JAS 1, 2011 | BZ7: No | CE7: No | CH7: 3 | CI7: 3 | CK7: NF
A8: 7 | B8: C1/007 | C8: Esnat | D8: Dorothy | E8: Chirwa | F8: Woman | G8: 1 | H8: Malawi | I8: University of Malawi and Associates | J8: Mathematical Sciences | K8: DPHRU Wits | L8: University of the Witwatersrand | M8: No | O8: Married | P8: Married | Q8: Married | R8: echirwa@cartafrica.org | S8: echirwa@chanco.unima.mw edkwalira@yahoo.com, | U8: Masters in Biometry (online) | V8: 26090 | W8: Modelling longitudinal child growth within the Birth to Twenty (Soweto) and Lungwena (Mangochi, Malawi) cohorts | X8: Field | Y8: No | Z8: Primary | AA8: 7.5 | AB8: 40577 | AC8: 40603 | AE8: Prof Shane Norris | AF8: Dr. Paula Griffiths | AG8: Assoc Prof. Ken Maleta | AH8: =COUNTA(AE8:AG8) -> 3 | AI8: Host | AJ8: Other | AK8: Home | AL8: Yes | AM8: No | AN8: No | AO8: Academic | AP8: Lecturer | AQ8: Senior Biostatistician | AR8: Yes | AT8: SOUTH AFRICA MEDICAL RESEARCH COUNCIL | AU8: 0000-0003-0471-4978 | AW8: 40634 | AX8: 40878 | AY8: Yes | BF8: 41456 | BG8: Yes | BH8: 41700 | BI8: Yes | BM8: 42674 | BN8: Completed | BO8: =DATEDIF(AW8,BM8, "M")+1 -> 67 | BP8: =DATEDIF(AX8,BM8, "M")+1 -> 59 | BR8: 1 | BS8: 7 | BT8: 47 | BU8: 3 | BV8: 0 | BW8: 0 | BX8: 0 | BY8: No | BZ8: No | CE8: No | CH8: 2 | CI8: 2 | CK8: NF
A9: 8 | B9: C1/008 | C9: Taofeek | D9: Oluwole | E9: Awotidebe | F9: Man | G9: 1 | H9: Nigeria | I9: Obafemi Awolowo University | J9: Exercise Physiology | K9: Human Kinetics and Health Education | L9: University of Ibadan | M9: No | N9: 125847 | O9: Married | P9: Married | R9: tawotidebe@cartafrica.org | S9: tidebet@yahoo.com | T9: +2348037196021 | U9: M.SC Physiotherapy | V9: 26085 | W9: Cardiovascular Risk Profile And Physical Activity Level of Residents of a Semi – Urban Community In Nigeria | X9: Field | Y9: No | Z9: Primary | AA9: 14 | AB9: 40739 | AC9: 40603 | AE9: Professor Babalola Joseph Folorunso | AF9: Professor Lateef Babatunde Salako | AH9: =COUNTA(AE9:AG9) -> 2 | AI9: Other | AL9: Yes | AO9: Academic | AP9: Lecturer II | AQ9: Senior Lecturer | AR9: Yes | AS9: Vice Dean of the Faculty of Basic Medical Sciences, College of Health Sciences | AT9: OBAFEMI AWOLOWO UNIVERSITY | AU9: 0000-0002-8583-9467 | AW9: 40634 | AX9: 40878 | AY9: Yes | BF9: 41456 | BG9: Yes | BH9: 41701 | BI9: Yes | BM9: 42325 | BN9: Completed | BO9: =DATEDIF(AW9,BM9, "M")+1 -> 56 | BP9: =DATEDIF(AX9,BM9, "M")+1 -> 48 | BR9: 5 | BS9: 12 | BT9: 10 | BU9: 6 | BV9: 4 | BW9: 2 | BX9: 0 | BY9: No | BZ9: No | CE9: No | CH9: NF | CI9: NF | CK9: NF
A10: 9 | B10: C1/009 | C10: Fresier | E10: Maseko | F10: Man | G10: 1 | H10: Malawi | I10: University of Malawi and Associates | J10: Community Health | K10: Department of Community Health | L10: University of Malawi and Associates | M10: Yes | P10: NF | R10: fmaseko@cartafrica.org | S10: fcmaseko@yahoo.com fmaseko@medcol.mw | U10: Master of Public Health(online) | V10: 26541 | W10: Maximizing utilization of cervical cancer prevention services in South East Health Zone of Malawi. What would it take? | X10: Field | Y10: No | Z10: Primary | AA10: 11 | AB10: 40544 | AC10: 40603 | AE10: Dr. Maureen Leah Chirwa | AF10: Dr. Adamson Muula | AH10: =COUNTA(AE10:AG10) -> 2 | AI10: Home | AJ10: Host | AL10: Yes | AM10: Yes | AO10: Academic | AQ10: Lecturer | AT10: UNIVERSITY OF MALAWI | AU10: 0000-0002-0996-4207 | AW10: 40634 | AX10: 40878 | AY10: Yes | BF10: 41456 | BG10: Yes | BH10: 41702 | BI10: Yes | BM10: 42613 | BN10: Completed | BO10: =DATEDIF(AW10,BM10, "M")+1 -> 65 | BP10: =DATEDIF(AX10,BM10, "M")+1 -> 57 | BR10: 7 | BS10: 6 | BT10: 1 | BU10: 3 | BV10: 1 | BW10: 0 | BX10: 0 | BY10: No | BZ10: No | CE10: No | CH10: NF | CI10: NF | CK10: NF
A11: 10 | B11: C1/010 | C11: François | E11: Niragire | F11: Man | G11: 1 | H11: Rwanda | I11: University of Rwanda | J11: Statistics | K11: Applied Statistics | L11: University of Rwanda | M11: Yes | N11: 213004253 | O11: Married | P11: Married | Q11: Married | R11: fniragire@cartafrica.org | S11: fniragire@ur.ac.rw; fniragiree@gmail.com; fniragire@gmail.com | T11: +250 78 8273787/+250787427688 | U11: MSc. In Social Statistics | V11: 26915 | W11: Spatial modeling of the relationship between HIV prevalence and socioeconomic determinants of child mortality in Rwanda. | X11: Field | Y11: No | Z11: Secondary | AA11: 13 | AB11: 40823 | AC11: 40603 | AE11: Dr. Thomas N. O. Achia | AF11: Dr. Lyambabaje Alexandre | AG11: Joseph Ntaganira | AH11: =COUNTA(AE11:AG11) -> 3 | AI11: Other | AJ11: Home | AK11: Home | AL11: Yes | AM11: Yes | AN11: No | AO11: Academic | AP11: Assistant Lecturer | AQ11: Professor | AR11: Yes | AS11: Director of Teaching and Learning, Director of Research and Innovation at he College of Business and Economics (2022) | AT11: UNIVERSITY OF RWANDA | AU11: 0000-0003-0473-387 | AW11: 40634 | AX11: 40878 | AY11: Yes | AZ11: 40672 | BB11: 41298 | BF11: 41484 | BG11: Yes | BH11: 41703 | BI11: Yes | BJ11: 42507 | BK11: 42947 | BL11: 42967 | BM11: 42947 | BN11: Completed | BO11: =DATEDIF(AW11,BM11, "M")+1 -> 76 | BP11: =DATEDIF(AX11,BM11, "M")+1 -> 68 | BQ11: Spatial modelling of the relationship between HIV prevalence and determinants of child mortality in Rwanda | BR11: 0 | BS11: 4 | BT11: 9 | BU11: 1 | BV11: 4 | BW11: 0 | BX11: 0 | BY11: No | BZ11: No | CE11: No | CH11: 3 | CI11: 4 | CK11: NF
A12: 11 | B12: C1/011 | C12: Joshua | D12: Odunayo | E12: Akinyemi | F12: Man | G12: 1 | H12: Nigeria | I12: University of Ibadan | J12: Epidemiology & Medical Statistics | K12: Epidemiology and Medical Statistics | L12: University of Ibadan | M12: Yes | O12: Single | P12: Married | Q12: Married | R12: jakinyemi@cartafrica.org | S12: odunjoshua@yahoo.com joakinyemi@com.ui.edu.ng | T12: +234-8077677427 | U12: MSc (Medical Statistics) | V12: 28098 | W12: Levels, Trends and Differentials of Infant and Child Mortality in Nigeria: 1990 - 2008 | X12: Field | Y12: No | Z12: Secondary | AA12: 21 | AB12: 40609 | AC12: 40603 | AE12: Prof Afolabi Bamgboye | AF12: Prof. Olusola Ayeni | AH12: =COUNTA(AE12:AG12) -> 2 | AI12: Home | AJ12: Host | AL12: Yes | AM12: No | AO12: Academic | AP12: Lecturer | AQ12: Professor | AR12: Yes | AT12: UNIVERSITY OF IBADAN | AU12: 0000-0002-0675-2110 | AW12: 40634 | AX12: 40878 | AY12: Yes | BF12: 41456 | BG12: Yes | BH12: 41704 | BI12: Yes | BM12: 41671 | BN12: Completed | BO12: =DATEDIF(AW12,BM12, "M")+1 -> 35 | BP12: =DATEDIF(AX12,BM12, "M")+1 -> 27 | BQ12: Levels, Trends and Differentials in Under-five Mortality in Nigeria (1990-2008) | BR12: 18 | BS12: 14 | BT12: 117 | BU12: 4 | BV12: 2 | BW12: 7 | BX12: 6 | BY12: No | BZ12: No | CE12: No | CH12: 0 | CI12: 2 | CK12: NF
A13: 12 | B13: C1/012 | C13: Mphatso | D13: Steve Wilbes | E13: Kamndaya | F13: Man | G13: 1 | H13: Malawi | I13: University of Malawi and Associates | J13: Mathematics and Statistics | L13: University of the Witwatersrand | M13: No | O13: Married | P13: Married | Q13: Married | R13: mkamndaya@cartafrica.org | S13: kamndayam@yahoo.com | T13: +265999851477 | U13: MSc Mathematical Statistics | V13: 27918 | W13: Modeling indoor air pollution to improve health delivery systems and public health in Malawi | X13: Field | Y13: No | Z13: Primary | AA13: 18 | AB13: 40612 | AC13: 40603 | AE13: Lawrence N.M. Kazembe | AF13: Dr. Liz Thomas | AH13: =COUNTA(AE13:AG13) -> 2 | AI13: Home | AJ13: Host | AL13: Yes | AM13: No | AO13: Academic | AP13: Lecturer | AQ13: Associate Professor | AR13: Yes | AT13: UNIVERSITY OF MALAWI | AU13: 0000-0002-7597-3339 | AW13: 40634 | AX13: 40878 | AY13: Yes | BB13: 41193 | BE13: Multilevel analysis of determinants of HIV- related sexual risks-taking and decision making among youths in urban informal settlements in Malawi and South Africa | BF13: 41456 | BG13: Yes | BH13: 41705 | BI13: Yes | BM13: 42460 | BN13: Completed | BO13: =DATEDIF(AW13,BM13, "M")+1 -> 60 | BP13: =DATEDIF(AX13,BM13, "M")+1 -> 52 | BR13: 0 | BS13: 5 | BT13: 10 | BU13: 5 | BV13: 0 | BW13: 0 | BX13: 0 | BY13: No | BZ13: No | CE13: No | CH13: 1 | CI13: 2 | CK13: NF
A14: 13 | B14: C1/013 | C14: Esther | D14: Clyde | E14: Nabakwe | F14: Woman | G14: 1 | H14: Kenya | I14: Moi University | J14: Pediatrics & Child health | L14: Moi University | M14: Yes | O14: Single | P14: Single | Q14: Single | R14: nabakwe@cartafrica.org | S14: echirwa@chanco.unima.mw edkwalira@yahoo.com | U14: M.Med Paediatrics | V14: 23063 | W14: Socio-cultural and economic determinants of HIV mothers' knowledge, attitude and practise of current WHO infant feeding policy and the impact on infants' outcome | X14: Field | Y14: No | Z14: Primary | AA14: 25 | AB14: 40605 | AC14: 40603 | AE14: Prof Joshua Akong’a | AF14: Dr. Grace Ettyang | AH14: =COUNTA(AE14:AG14) -> 2 | AI14: Home | AJ14: Host | AL14: Yes | AM14: Yes | AO14: Academic | AQ14: Senior Lecturer | AT14: MOI UNIVERSITY | AU14: 0000-0002-0401-3373 | AW14: 40634 | AX14: 40878 | AY14: Yes | AZ14: 40665 | BA14: 40727 | BF14: 41456 | BG14: Yes | BH14: 41706 | BI14: Yes | BM14: 43699 | BN14: Completed | BO14: =DATEDIF(AW14,BM14, "M")+1 -> 101 | BP14: =DATEDIF(AX14,BM14, "M")+1 -> 93 | BQ14: Sex and young people in urban slums: Exploring the material deprivation and sexual risk nexus in Malawi and South Africa | BR14: 4 | BS14: 4 | BT14: 2 | BU14: 0 | BV14: 0 | BW14: 0 | BX14: 0 | BY14: No | BZ14: No | CE14: No | CH14: 3 | CI14: 3 | CK14: NF
A15: 14 | B15: C1/014 | C15: Nicole | E15: De Wet | F15: Woman | G15: 1 | H15: South Africa | I15: University of the Witwatersrand | J15: Demography | K15: Demography and Population Studies | L15: University of the Witwatersrand | M15: Yes | N15: 0211542Y | O15: Single | P15: Married | Q15: Single | R15: ndewet@cartafrica.org | S15: nicole.dewet@wits.ac.za Nic_dewet@yahoo.com | U15: Master of Arts Demography and Population Studies | V15: 30815 | W15: Domestic Violence and child health outcomes: An investigation into the relationship between frequency of abuse and negative child health outcomes in two African countries. | X15: Field | Y15: No | Z15: Primary | AA15: 22.5 | AB15: 40605 | AC15: 40603 | AE15: Prof Clifford Odimegwu | AH15: =COUNTA(AE15:AG15) -> 1 | AI15: Home | AL15: No | AO15: Academic | AP15: Tutor | AQ15: Associate Professor | AR15: Yes | AS15: Assistant Dean for Postgraduate Studies, Faculty of Humanities | AT15: UNIVERSITY OF THE WITWATERSRAND | AU15: 0000-0001-5750-2851 | AW15: 40634 | AX15: 40878 | AY15: Yes | BF15: 41456 | BG15: Yes | BH15: 41707 | BI15: Yes | BM15: 41608 | BN15: Completed | BO15: =DATEDIF(AW15,BM15, "M")+1 -> 32 | BP15: =DATEDIF(AX15,BM15, "M")+1 -> 24 | BR15: 0 | BS15: 2 | BT15: 56 | BU15: 4 | BV15: 6 | BW15: 11 | BX15: 7 | BY15: No | BZ15: No | CE15: No | CH15: 0 | CI15: 0 | CK15: NF
A16: 15 | B16: C1/015 | C16: Kennedy | D16: S.Naviava | E16: Otwombe | F16: Man | G16: 1 | H16: South Africa | I16: University of the Witwatersrand | J16: Epidemiology & Medical Biostatistics | K16: Perinatal HIV Research Unit, Dept. Data and Statistics | L16: University of the Witwatersrand | M16: Yes | O16: Married | P16: Married | Q16: Married | R16: otwombek@phru.co.za | S16: otwombek@phru.co.za | U16: M.Sc Mathematical statistics | V16: 26801 | W16: Use of frailty modeling with arbitrary censoring in determining predictors of mortality for a Clinical researchized HIV positive population in South Africa | X16: Clinical research | Y16: No | Z16: Secondary | AA16: 21 | AB16: 40638 | AC16: 40603 | AE16: Dr. Tobias Chirwa | AF16: Dr. Guy de Bruyn | AH16: =COUNTA(AE16:AG16) -> 2 | AI16: Home | AJ16: Home | AL16: Yes | AM16: No | AO16: Other | AP16: Senior Statistician | AQ16: Associate Professor | AR16: Yes | AT16: UNIVERSITY OF THE WITWATERSRAND | AU16: 0000-0002-7433-4383 | AW16: 40634 | AX16: 40878 | AY16: Yes | BF16: 41456 | BG16: Yes | BH16: 41708 | BI16: Yes | BM16: 43285 | BN16: Completed | BO16: =DATEDIF(AW16,BM16, "M")+1 -> 88 | BP16: =DATEDIF(AX16,BM16, "M")+1 -> 80 | BR16: 8 | BS16: 45 | BT16: 55 | BU16: 5 | BV16: 2 | BW16: 0 | BX16: 0 | BY16: No | BZ16: No | CE16: No | CH16: 2 | CI16: 2 | CK16: NF
A17: 16 | B17: C1/016 | C17: Peter | D17: Suriwakenda | E17: Nyasulu | F17: Man | G17: 1 | H17: Malawi | I17: University of the Witwatersrand | J17: Epidemiology & Medical Biostatistics | K17: Division of Epidemiology & Medical Biostatistics | L17: University of the Witwatersrand | M17: Yes | P17: Married | R17: pnyasulu@cartafrica.org | S17: Peter.Nyasulu@wits.ac.za | U17: M.Sc (Medicine) | V17: 25201 | W17: Surveillance of antimicrobial susceptibility patterns among pathogens isolated in public sector Clinical researchs associated with academic institutions, South Africa during a 5 year period 2005-2009 | X17: Clinical research - Retrospective | Y17: yes | Z17: Secondary | AA17: 11 | AB17: 40605 | AC17: 40603 | AE17: Prof Jill Murray | AF17: Prof. Hendrik J. Koornhof | AG17: Dr. Olga Perovic | AH17: =COUNTA(AE17:AG17) -> 3 | AI17: Home | AJ17: Home | AK17: Home | AL17: Yes | AM17: No | AN17: No | AO17: Academic | AQ17: Associate Professor | AR17: Yes | AT17: STELLENBOSCH UNIVERSITY | AU17: 0000-0003-2757-0663 | AW17: 40634 | AX17: 40878 | AY17: Yes | BF17: 41456 | BG17: Yes | BH17: 41709 | BI17: Yes | BM17: 41912 | BN17: Completed | BO17: =DATEDIF(AW17,BM17, "M")+1 -> 42 | BP17: =DATEDIF(AX17,BM17, "M")+1 -> 34 | BR17: 3 | BS17: 10 | BT17: 77 | BU17: 4 | BV17: 10 | BW17: 6 | BX17: 9 | BY17: No | BZ17: No | CE17: No | CH17: NF | CI17: NF | CK17: NF
A18: 17 | B18: C1/017 | C18: Rose | D18: Okoyo | E18: Opiyo | F18: Woman | G18: 1 | H18: Kenya | I18: University of Nairobi | J18: Nutrition | K18: Food Science, Nutrition and Technology | L18: University of Nairobi | M18: Yes | N18: A80/82301/2011 | O18: Married | P18: Married | Q18: Married | R18: ropiyo@cartafrica.org | S18: roseopiyo@uonbi.ac.ke roseopiyo04@yahoo.co.uk | T18: +254 722473122 | U18: Msc Applied Human Nutrition | V18: 22992 | W18: Effect of Omega-3 Fatty Acids (Fish Oil) Supplementation along with Diet on Depression and Nutrition Status of HIV-Seropositive and HIV-Seronegative Pregnant Mothers among Low-income Urban Population in Nairobi | X18: Clinical research - RCT | Y18: yes | Z18: Primary | AA18: 17 | AB18: 40801 | AC18: 40603 | AE18: Prof. Wambui Kogi-Makau | AF18: Prof. Koigi R. Kamau | AG18: Dr. Anne Obondo | AH18: =COUNTA(AE18:AG18) -> 3 | AI18: Home | AJ18: Home | AK18: Home | AL18: Yes | AM18: No | AN18: No | AO18: Academic | AP18: Lecturer | AQ18: Senior Lecturer | AR18: Yes | AS18: Member of College of Health Sciences, University of Nairobi Committee on Guidelines for PhD Equivalent Qualifications for Clinicians. | AT18: UNIVERSITY OF NAIROBI | AU18: 0000-0003-1885-9991 | AW18: 40634 | AX18: 40878 | AY18: Yes | BE18: Effect of fish oil Omega- 3 fatty acids on reduction of depressive symptoms among HIV - seropositive pregnant women | BF18: 41456 | BG18: Yes | BH18: 41710 | BI18: Yes | BM18: 42277 | BN18: Completed | BO18: =DATEDIF(AW18,BM18, "M")+1 -> 54 | BP18: =DATEDIF(AX18,BM18, "M")+1 -> 46 | BQ18: Effect of fish oil Omega- 3 fatty acids on reduction of depressive symptoms among HIV - seropositive pregnant women | BS18: 3 | BT18: 8 | BU18: 1 | BV18: 1 | BW18: 1 | BX18: 0 | BY18: No | BZ18: No | CE18: No | CH18: 2 | CI18: 2 | CK18: NF
A19: 18 | B19: C1/018 | C19: Sunday | D19: Adepoju | E19: Adedini | F19: Man | G19: 1 | H19: Nigeria | I19: Obafemi Awolowo University | J19: Demography and Population Studies | K19: Demography and Population Studies | L19: University of the Witwatersrand | M19: No | N19: 560454 | O19: Married | P19: Married | Q19: Married | R19: sadedini@cartafrica.org | S19: sunday.adedini@gmail.com adedinisunday@yahoo.com | T19: +234-803 397 7498 | U19: M.Sc Demography and Social Statistics | V19: 27511 | W19: Multilevel Analysis of Determinants of Infant and Child Mortality in West Africa | X19: Field | Y19: No | Z19: Secondary | AA19: 13 | AB19: 40582 | AC19: 40603 | AE19: Prof Clifford Odimegwu | AF19: Dr. Samson Bamiwuye | AH19: =COUNTA(AE19:AG19) -> 2 | AI19: Host | AJ19: Home | AL19: Yes | AM19: Yes | AO19: Academic | AP19: Lecturer | AQ19: Professor | AR19: Yes | AS19: Head Demographer; Head of Demography and Social Statistics (2021) | AT19: FEDERAL UNIVERSITY, OYE-EKITI (2020) | AU19: 0000-0003-0378-1941 | AW19: 40634 | AX19: 40878 | AY19: Yes | BF19: 41456 | BG19: Yes | BH19: 41711 | BI19: Yes | BM19: 41334 | BN19: Completed | BO19: =DATEDIF(AW19,BM19, "M")+1 -> 24 | BP19: =DATEDIF(AX19,BM19, "M")+1 -> 16 | BR19: NF | BS19: 4 | BT19: 43 | BU19: 6 | BV19: 4 | BW19: 6 | BX19: 6 | BY19: No | BZ19: No | CE19: No | CH19: 3 | CI19: 3 | CK19: NF
A20: 19 | B20: C1/019 | C20: Sulaimon | D20: Taiwo | E20: Adedokun | F20: Man | G20: 1 | H20: Nigeria | I20: Obafemi Awolowo University | J20: Demography and Social Statistics | K20: Demography and Social Statistics | L20: Obafemi Awolowo University | M20: Yes | O20: Married | P20: Married | Q20: Married | R20: sadedokun@cartafrica.org | S20: adedokunsulait@gmail.com | T20: +2348051398276 | U20: M.Sc Demography and Social Statistics | V20: 26644 | W20: Maternal and Socio-demographic Correlates of Under-five Mortality in Yobe State, Nigeria | X20: Field | Y20: No | Z20: Secondary | AA20: 21.5 | AB20: 40605 | AC20: 40603 | AE20: Ogunjuyigbe Peter Olasupo | AH20: =COUNTA(AE20:AG20) -> 1 | AI20: Home | AL20: Yes | AO20: Academic | AP20: Lecturer II | AQ20: Associate Professor | AR20: Yes | AT20: OBAFEMI AWOLOWO UNIVERSITY | AU20: 0000-0003-0021-8045 | AW20: 40634 | AX20: 40878 | AY20: Yes | BB20: 41225 | BE20: Comparative analysis of the factors accounting for under-five mortality differentials in North East and South West of Nigeria | BF20: 41456 | BG20: Yes | BH20: 42064 | BI20: No | BM20: 41395 | BN20: Completed | BO20: =DATEDIF(AW20,BM20, "M")+1 -> 26 | BP20: =DATEDIF(AX20,BM20, "M")+1 -> 18 | BQ20: Comparative analysis of the factors accounting for under-five mortality differentials in North East and South West of Nigeria | BT20: 12 | BU20: 0 | BV20: 0 | BW20: 4 | BX20: 1 | BY20: No | BZ20: No | CE20: No | CH20: 3 | CI20: 5 | CK20: NF
A21: 20 | B21: C1/020 | C21: Sulaimon | D21: Atolagbe | E21: Afolabi | F21: Man | G21: 1 | H21: Nigeria | I21: AGINCOURT | J21: Demography & Population Studies | K21: Demography & Population Studies | L21: University of the Witwatersrand | M21: No | N21: 0607789e | P21: Married | R21: safolabi@cartafrica.org | S21: afolaborn@gmail.com | T21: +2771718311 | U21: MA in Demography and Population studies | V21: 28744 | W21: License to move: a longitudinal study of migration and its relation to HIV and TB in high mortality post-apartheid South Africa. | X21: Field | Y21: yes | Z21: Primary | AA21: 12 | AB21: 40609 | AC21: 40603 | AE21: Dr. Mark Collinson | AF21: Prof. Philippe Bocquier | AH21: =COUNTA(AE21:AG21) -> 2 | AI21: Home | AJ21: Host | AL21: Yes | AM21: No | AO21: Other | AQ21: Lead Data Scientist | AT21: UNIVERSITY OF THE WITWATERSRAND | AU21: 0000-0001-9382-6386 | AW21: 40634 | AX21: 40878 | AY21: Yes | BF21: 41456 | BG21: Yes | BH21: 41712 | BI21: Yes | BM21: 43073 | BN21: Completed | BO21: =DATEDIF(AW21,BM21, "M")+1 -> 81 | BP21: =DATEDIF(AX21,BM21, "M")+1 -> 73 | BR21: 1 | BS21: 8 | BT21: 3 | BU21: 0 | BV21: 0 | BW21: 0 | BX21: 0 | BY21: No | BZ21: No | CE21: No | CH21: NF | CI21: NF | CK21: NF | CL21: Deceased 15/02/2021
A22: 22 | B22: C1/022 | C22: Theresa | D22: Njeri | E22: Kinyari | F22: Woman | G22: 1 | H22: Kenya | I22: University of Nairobi | N22: NF | O22: NF | P22: NF | Q22: NF | AC22: 40603 | AD22: 40865 | AH22: =COUNTA(AE22:AG22) -> 0 | AW22: 40634 | BN22: Terminated | BO22: Terminated | BY22: No | CK22: NF
A23: 23 | B23: C1/023 | C23: Peter | D23: Mwamba | E23: Maturi | F23: Man | G23: 1 | H23: Kenya | I23: University of Nairobi | L23: University of Nairobi | M23: Yes | N23: NF | O23: NF | P23: NF | Q23: NF | AC23: 40603 | AD23: 42613 | AH23: =COUNTA(AE23:AG23) -> 0 | AW23: 40634 | BN23: Terminated | BO23: Terminated | BY23: No | CK23: NF
A24: 24 | B24: C1/024 | C24: Jaclkline | D24: Halima | E24: Mgumia | F24: Woman | G24: 1 | H24: Tanzania | I24: University of Dar es Salaam | N24: NF | O24: NF | P24: NF | Q24: NF | AC24: 40603 | AD24: 41274 | AH24: =COUNTA(AE24:AG24) -> 0 | AW24: 40634 | BN24: Terminated | BO24: Terminated | BY24: No | CK24: NF
A25: 26 | B25: C2/001 | C25: Adebolajo | E25: Adeyemo | F25: Man | G25: 2 | H25: Nigeria | I25: University of Ibadan | J25: Epidemiology | L25: University of Ibadan | M25: Yes | O25: Married | P25: Married | R25: aadeyemo@cartafrica.org | S25: adebolajo@hotmail.com | U25: M.Sc Immunology | V25: 27062 | W25: Genetic epidemiology in Nigeria | X25: Field | Y25: yes | Z25: Primary | AA25: 13.5 | AB25: 40924 | AC25: 40969 | AE25: Prof. Odunayo Moronfoluwa Oluwatosin | AF25: Prof. Omotade Olayemi Olufemi-Julius | AH25: =COUNTA(AE25:AG25) -> 2 | AI25: Home | AJ25: Home | AL25: Yes | AM25: No | AO25: Academic | AP25: Assistant lecturer | AQ25: Senior Medical Research Fellow | AR25: Yes | AT25: UNIVERSITY OF IBADAN | AU25: 0000-0002-7486-5758 | AW25: 40969 | AX25: 41214 | AY25: Yes | BF25: 41852 | BG25: Yes | BH25: 42064 | BI25: Yes | BM25: 45183 | BN25: Completed | BO25: =DATEDIF(AW25,BM25, "M")+1 -> 139 | BP25: =DATEDIF(AX25,BM25, "M")+1 -> 131 | BR25: 1 | BS25: 14 | BT25: 0 | BU25: 1 | BV25: 0 | BW25: 0 | BX25: 0 | BY25: No | BZ25: 0 | CE25: No | CH25: 2 | CI25: NF | CK25: NF
A26: 27 | B26: C2/002 | C26: Alinane Linda | E26: Nyondo-Mipando | F26: Woman | G26: 2 | H26: Malawi | I26: University of Malawi and Associates | J26: Health Systems and Policy | K26: Health Systems and Policy | L26: University of Malawi and Associates | M26: Yes | N26: - | O26: Married | P26: Married | Q26: Married | R26: alinda@cartafrica.org | S26: lindaalinane@gmail.com | T26: +265 999 44 1212 | U26: Master of Nursing (Community Health) Online | V26: 28103 | W26: The feasibility of male involvement in Prevention of Mother to Child Transmission of HIV services in Malawi. | X26: Field | Y26: No | Z26: Primary | AA26: 18 | AB26: 40917 | AC26: 40969 | AE26: Dr. Angela Chimwaza | AF26: Dr. Adamson Muula | AH26: =COUNTA(AE26:AG26) -> 2 | AI26: Home | AJ26: Home | AL26: Yes | AM26: Yes | AO26: Academic | AP26: Project Coordinator | AQ26: Associate Professor | AR26: Yes | AS26: Deputy Dean, SPH and coordinator of Postgraduate Programs, School of Governance | AT26: UNIVERSITY OF LIVERPOOL, DEPARTMENT OF WOMEN'S AND CHILDREN'S HEALTH (2022) | AU26: 0000-0002-3572-3810 | AW26: 40969 | AX26: 41214 | AY26: Yes | BF26: 41852 | BG26: Yes | BH26: 42064 | BI26: Yes | BM26: 42460 | BN26: Completed | BO26: =DATEDIF(AW26,BM26, "M")+1 -> 49 | BP26: =DATEDIF(AX26,BM26, "M")+1 -> 41 | BR26: 0 | BS26: 4 | BT26: 36 | BU26: 1 | BV26: 0 | BW26: 1 | BX26: 1 | BY26: No | BZ26: 0 | CE26: No | CH26: 2 | CI26: 2 | CK26: FF
A27: 28 | B27: C2/003 | C27: Austin | D27: Henderson | E27: Mtethiwa | F27: Man | G27: 2 | H27: Malawi | I27: University of Malawi and Associates | J27: Environmental Sciences | L27: University of Malawi and Associates | M27: Yes | P27: NF | R27: amtethiwa@cartafrica.org | T27: +265888316331 | U27: M. Sc Limnology & Wetland Ecosystems | V27: 26796 | W27: Contribution of domestic waste water treatment plants to proliferation of schistosomiasis and pollution of aquatic resources and ability herbaceous plants for waste water treatment | X27: Field | Y27: yes | Z27: Primary | AA27: 12 | AB27: 40977 | AC27: 40969 | AE27: Wilson Mandala | AF27: Dr. Lucy Namkinga | AH27: =COUNTA(AE27:AG27) -> 2 | AI27: Home | AJ27: Other | AL27: Yes | AM27: Yes | AO27: Academic | AP27: Lecturer | AQ27: Associate Professor | AR27: Yes | AT27: UNIVERSITY OF MALAWI | AU27: 0000-0003-0793-5186 | AW27: 40969 | AX27: 41214 | AY27: Yes | BF27: 41852 | BG27: Yes | BH27: 42064 | BI27: Yes | BM27: 42704 | BN27: Completed | BO27: =DATEDIF(AW27,BM27, "M")+1 -> 57 | BP27: =DATEDIF(AX27,BM27, "M")+1 -> 49 | BR27: 2 | BS27: 1 | BT27: 9 | BU27: 1 | BV27: 1 | BW27: 0 | BX27: 0 | BY27: No | BZ27: 0 | CE27: No | CH27: NF | CI27: NF | CK27: CARNEGIE 2
A28: 29 | B28: C2/004 | C28: Diana | D28: - | E28: Menya | F28: Woman | G28: 2 | H28: Kenya | I28: Moi University | J28: Medical Epidemiology | K28: Library | L28: Moi University | M28: Yes | O28: Married | P28: Married | R28: dmenya@cartafrica.org | S28: dianamenya@gmail.com | T28: +254 720352579/+254 733777500 | U28: MSc. Clinical Epidemiology | V28: 27531 | X28: Clinical research | Y28: unkown | Z28: Primary | AB28: 41334 | AC28: 40969 | AE28: Prof. Odipo Osano | AF28: Prof Rafael Carel | AH28: =COUNTA(AE28:AG28) -> 2 | AI28: Other | AJ28: Other | AL28: No | AM28: No | AO28: Academic | AP28: Senior Lecturer | AQ28: Associate Professor | AR28: Yes | AT28: MOI UNIVERSITY | AU28: 000 0000337081871 | AW28: 40969 | AX28: 41214 | AY28: Yes | BF28: 41852 | BG28: Yes | BH28: 42064 | BI28: Yes | BM28: 42704 | BN28: Completed | BO28: =DATEDIF(AW28,BM28, "M")+1 -> 57 | BP28: =DATEDIF(AX28,BM28, "M")+1 -> 49 | BQ28: Behavioral, Nutritional and Environmental Factors associated with Esophageal Cancer in western Kenya | BR28: 8 | BS28: 19 | BT28: 43 | BU28: 2 | BV28: 2 | BW28: 1 | BX28: 0 | BY28: No | BZ28: 0 | CE28: No | CH28: 2 | CI28: 2 | CJ28: 2 | CK28: NF
A29: 30 | B29: C2/005 | C29: Evaline | E29: Mcharo | F29: Woman | G29: 2 | H29: Tanzania | I29: University of Dar es Salaam | J29: Epidemiology | K29: Geography | L29: University of Nairobi | M29: No | O29: Single | P29: Single | Q29: Single | R29: emcharo@cartafrica.org | S29: mcharoevaline@gmail.com; evalinemcharo@yahoo.co.uk | U29: MA in demography (online) | V29: 29064 | W29: Socioeconomic determinants of unsafe abortion and its implication to women in Tanzania. | X29: Field | Y29: No | Z29: Primary | AA29: 21.5 | AB29: 40946 | AC29: 40969 | AE29: Dr. Lawrence Ikamari | AF29: Dr. Alfred Agwanda Otieno | AH29: =COUNTA(AE29:AG29) -> 2 | AI29: Host | AJ29: Host | AL29: Yes | AM29: Yes | AO29: Researcher | AP29: Assistant Lecturer | AQ29: Lecturer | AR29: Yes | AT29: UNIVERSITY OF DAR ES SALAAM | AW29: 40969 | AX29: 41214 | AY29: Yes | BF29: 41852 | BG29: Yes | BH29: 42064 | BI29: Yes | BM29: 42735 | BN29: Completed | BO29: =DATEDIF(AW29,BM29, "M")+1 -> 58 | BP29: =DATEDIF(AX29,BM29, "M")+1 -> 50 | BR29: NF | BS29: 0 | BT29: 1 | BU29: 0 | BV29: 0 | BW29: 0 | BX29: 1 | BY29: No | BZ29: 0 | CE29: No | CH29: NF | CI29: NF | CK29: WT
A30: 31 | B30: C2/006 | C30: Stephen | D30: Ojiambo | E30: Wandera | F30: Man | G30: 2 | H30: Uganda | I30: Makerere University | J30: Epidemiology | K30: Department of Population Studies | L30: Makerere University | M30: Yes | O30: Married | P30: married | Q30: Married | R30: swandera@cartafrica.org | S30: swandera@gmail.com | T30: +256774976879 | U30: M.Sc Population & Reproductive Health | V30: 30697 | W30: Intergenerational Support and Health of the Ageing Population In Rural Uganda | X30: Field | Y30: No | Z30: Primary | AA30: 2 | AB30: 40946 | AC30: 40969 | AE30: Dr. James Ntozi | AF30: Dr. Betty Kwagala | AH30: =COUNTA(AE30:AG30) -> 2 | AI30: Home | AJ30: Home | AL30: Yes | AM30: No | AO30: Academic | AP30: Assistant Lecturer | AQ30: Senior Lecturer | AR30: Yes | AS30: Head of Department | AT30: MAKERERE UNIVERISTY | AU30: 0000-0002-5617-0274 | AW30: 40969 | AX30: 41214 | AY30: Yes | BE30: Disaparities in health and access to healthcare among older persons in Uganda | BF30: 41852 | BG30: Yes | BH30: 42064 | BI30: Yes | BM30: 42460 | BN30: Completed | BO30: =DATEDIF(AW30,BM30, "M")+1 -> 49 | BP30: =DATEDIF(AX30,BM30, "M")+1 -> 41 | BQ30: Disaparities in health and access to healthcare among older persons in Uganda | BR30: 0 | BS30: 10 | BT30: 16 | BU30: 6 | BV30: 2 | BW30: 2 | BX30: 0 | BY30: No | BZ30: 0 | CE30: No | CH30: 2 | CI30: 3 | CK30: WT
A31: 32 | B31: C2/007 | C31: Adeniyi | D31: Francis | E31: Fagbamigbe | F31: Man | G31: 2 | H31: Nigeria | I31: University of Ibadan | J31: BIOSTATISTICS | K31: EPIDEMIOLOGY AND MEDICAL STATISTICS | L31: University of Ibadan | M31: Yes | N31: 152419 | P31: Married | R31: fadeniyi@cartafrica.org | S31: franstel74@yahoo.com | T31: +2348061348165 | U31: Masters in medical statistics | V31: 27076 | W31: Modeling association between bivariate censored outcomes: a case study of bipolar disorder | X31: Field | Y31: No | Z31: Primary | AA31: 4 | AB31: 40987 | AC31: 40969 | AE31: Prof. Elijah Afolabi Bamgboye | AH31: =COUNTA(AE31:AG31) -> 1 | AI31: Home | AL31: Yes | AO31: Academic | AP31: Lecturer II | AQ31: Professor | AR31: Yes | AT31: UNIVERSITY OF IBADAN | AU31: 0000-0001-9184-8258 | AW31: 40969 | AX31: 41214 | AY31: Yes | BF31: 41852 | BG31: Yes | BH31: 42064 | BI31: Yes | BM31: 41729 | BN31: Completed | BO31: =DATEDIF(AW31,BM31, "M")+1 -> 25 | BP31: =DATEDIF(AX31,BM31, "M")+1 -> 17 | BR31: 6 | BS31: 6 | BT31: 93 | BU31: 8 | BV31: 4 | BW31: 18 | BX31: 4 | BY31: No | BZ31: 0 | CE31: No | CH31: NF | CI31: 2 | CK31: MAC
A32: 33 | B32: C2/008 | C32: Tumwine | E32: Gabriel | F32: Man | G32: 2 | H32: Uganda | I32: Makerere University | J32: Epidemiology | L32: Makerere University | M32: Yes | P32: NF | R32: gtumwine@cartafrica.org | S32: gtumwine@vetmed.mak.ac.ug; tumwinegabriel@gmail.com | T32: +256782194819 | U32: M.Sc Molecular Biology | V32: 29825 | W32: Malaria and filariasis co-infection during pregnancy in high malaria transmission areas of Uganda: Impacts on pregnancy outcomes, immune response and antifolates effects | X32: Clinical research | Y32: yes | Z32: Primary | AA32: 18.5 | AB32: 40933 | AC32: 40969 | AE32: Dr. Enock Matovu | AF32: Dr. Jean Langhorne | AH32: =COUNTA(AE32:AG32) -> 2 | AI32: Home | AJ32: Other | AL32: Yes | AM32: No | AO32: Academic | AP32: Teaching Assistant | AT32: MAKERERE UNIVERSITY | AU32: 0000-0003-3338-5333 | AW32: 40969 | AX32: 41214 | AY32: Yes | BF32: 41852 | BG32: Yes | BH32: 42064 | BI32: Yes | BN32: In progress | BR32: 1 | BS32: 9 | BT32: 0 | BU32: 1 | BV32: 0 | BW32: 0 | BX32: 0 | BY32: No | BZ32: 0 | CE32: No | CH32: 3 | CI32: NF | CK32: CARNEGIE 2
A33: 34 | B33: C2/009 | C33: Herbert | D33: Hudson | E33: Longwe | F33: Man | G33: 2 | H33: Malawi | I33: University of Malawi and Associates | J33: Epidemiology | K33: Department of Population Studies | L33: University of Malawi and Associates | M33: Yes | O33: Married | P33: Married | Q33: Married | R33: hlongwe@cartafrica.org | S33: Herbert.longwe@gmail.com, hlongwe@medcol.mw | U33: Master of Philosophy (Tropical Medicine). | V33: 29122 | W33: Investigating the effect of daily cotrimoxazole prophylaxis on the acquisition of malaria specific immunity in HIV exposed children and HIV infected children | X33: Clinical research | Y33: yes | Z33: Primary | AA33: 5.5 | AB33: 40961 | AC33: 40969 | AE33: Dr. Wilson Mandala | AF33: Dr. Adam Cunningham | AG33: Cal MacLennan | AH33: =COUNTA(AE33:AG33) -> 3 | AI33: Home | AJ33: Other | AL33: Yes | AM33: No | AP33: Research Scientist | AQ33: Deputy Director Laboratory Support, ICAP at Columbia University | AR33: Yes | AT33: COLUMBIA UNIVERSITY, SOUTH AFRICA | AU33: 0000-0002-2496-896X | AW33: 40969 | AX33: 41214 | AY33: Yes | BE33: Efect of daily contrimoxazole prophylaxis on naturally acquired plasmodium falciparum -Specific Immune Responses in HIV - exposed uninfected Malawian Children | BF33: 41852 | BG33: Yes | BH33: 42064 | BI33: Yes | BM33: 42185 | BN33: Completed | BO33: =DATEDIF(AW33,BM33, "M")+1 -> 40 | BP33: =DATEDIF(AX33,BM33, "M")+1 -> 32 | BQ33: Efect of daily contrimoxazole prophylaxis on naturally acquired plasmodium falciparum -Specific Immune Responses in HIV - exposed uninfected Malawian Children | BR33: 3 | BS33: 1 | BT33: 13 | BU33: 3 | BV33: 0 | BW33: 0 | BX33: 0 | BY33: No | BZ33: 0 | CE33: No | CH33: 1 | CI33: 2 | CK33: NF
A34: 35 | B34: C2/010 | C34: Joseph | D34: Maurice | E34: Mutisya | F34: Man | G34: 2 | H34: Kenya | I34: APHRC | J34: Public Health | K34: Education Research Program | L34: University of the Witwatersrand | M34: No | O34: Married | P34: Married | Q34: Married | R34: jmutisya@cartafrica.org | S34: mmutisya@aphrc.org mmutisya@ymail.com | T34: +25421987850 | U34: MSC (Population Based Epidemiology) | V34: 29322 | W34: Knowledge, Attitude and Beliefs on Stigma and Discrimination among people living with HIV & AIDS in Kenya: Individual and Community Level Effects | X34: Field | Y34: yes | Z34: Primary | AA34: 2 | AB34: 40987 | AC34: 40969 | AE34: Dr. Moses Ngware | AF34: Dr. Caroline Kabiru | AG34: Dr. Kandala Ngianga | AH34: =COUNTA(AE34:AG34) -> 3 | AI34: Home | AJ34: Home | AK34: Other | AL34: Yes | AM34: Yes | AN34: No | AO34: Researcher | AP34: Data Analyst | AQ34: Director Research at Zizi Afrique | AR34: Yes | AT34: ZIZI AFRIQUE FOUNDATION, KENYA (2022) | AU34: 0000-0001-5981-6344 | AW34: 40973 | AX34: 41225 | AY34: Yes | AZ34: 41740 | BB34: 41880 | BF34: 41852 | BG34: Yes | BH34: 42064 | BI34: Yes | BJ34: 42859 | BK34: 42859 | BL34: 43047 | BM34: 43438 | BN34: Completed | BO34: =DATEDIF(AW34,BM34, "M")+1 -> 81 | BP34: =DATEDIF(AX34,BM34, "M")+1 -> 73 | BQ34: Household food security, child Nutrition, and education: A longitudinal Analysis in Two urban informal Settlements in Kenya | BR34: 6 | BS34: 20 | BT34: 7 | BU34: 1 | BV34: 2 | BW34: 0 | BX34: 0 | BY34: No | BZ34: 0 | CE34: No | CH34: 1 | CI34: 3 | CK34: CARNEGIE 2
A35: 36 | B35: C2/011 | C35: Njuguna | D35: John | E35: Njenga | F35: Man | G35: 2 | H35: Kenya | I35: University of Nairobi | J35: Demography & Social statistics | K35: Population Studies and Research Institute (PSRI | L35: University of Nairobi | M35: Yes | P35: NF | R35: jnjega@cartafrica.org | T35: +254721473921 | U35: NF | V35: 26369 | W35: Determinants of Active Life Expectancy among Adult HIV/AIDS Patients in Kenya | X35: Field | Y35: No | Z35: Primary | AA35: 15 | AB35: 40959 | AC35: 40969 | AE35: Dr. Lawrence Ikamari | AF35: Dr. Murungaru Kimani | AH35: =COUNTA(AE35:AG35) -> 2 | AI35: Home | AJ35: Home | AL35: Yes | AM35: No | AO35: Academic | AT35: NF | AU35: 0000-0001-7130-1626 | AW35: 40969 | AX35: 41214 | AY35: Yes | BF35: 41852 | BG35: Yes | BH35: 42064 | BI35: Yes | BM35: 42735 | BN35: Completed | BO35: =DATEDIF(AW35,BM35, "M")+1 -> 58 | BP35: =DATEDIF(AX35,BM35, "M")+1 -> 50 | BR35: 1 | BS35: 6 | BT35: 6 | BU35: 0 | BV35: 0 | BW35: 0 | BX35: 0 | BY35: No | BZ35: 0 | CE35: No | CH35: NF | CI35: NF | CK35: WT
A36: 37 | B36: C2/012 | C36: Mary | D36: Oluwafunke | E36: Obiyan | F36: Woman | G36: 2 | H36: Nigeria | I36: Obafemi Awolowo University | J36: Demography | K36: Demography and Social Statistics | L36: Obafemi Awolowo University | M36: Yes | O36: Married | P36: Married | Q36: Married | R36: mobiyan@cartafrica.org | S36: maryobiyan@gmail.com | T36: +2348038161303 | U36: M.Sc Demography and Social Statistics | V36: 29380 | W36: Wealth Quintile and Fertility Differentials among Households in Nigeria | X36: Field | Y36: No | Z36: Primary | AA36: 11 | AB36: 40961 | AC36: 40969 | AE36: Prof. Peter O. Ogunjuyigbe | AF36: Ambrose Akinlo | AH36: =COUNTA(AE36:AG36) -> 2 | AI36: Home | AL36: Yes | AO36: Academic | AP36: Lecturer II | AQ36: Senior Lecturer | AR36: Yes | AT36: OBAFEMI AWOLOWO UNIVERSITY | AU36: 0000-0003-3583-0138 | AW36: 40969 | AX36: 41214 | AY36: Yes | BF36: 41852 | BG36: Yes | BH36: 42064 | BI36: Yes | BM36: 41729 | BN36: Completed | BO36: =DATEDIF(AW36,BM36, "M")+1 -> 25 | BP36: =DATEDIF(AX36,BM36, "M")+1 -> 17 | BR36: 1 | BS36: 0 | BT36: 12 | BU36: 1 | BV36: 0 | BW36: 1 | BX36: 0 | BY36: GW, 2016 | BZ36: 0 | CE36: No | CH36: 2 | CI36: 3 | CK36: WT
A37: 38 | B37: C2/013 | C37: Abiodun | D37: Olufunke | E37: Oluwatoba | F37: Woman | G37: 2 | H37: Nigeria | I37: University of Ibadan | J37: Environmental Sciences | L37: University of Ibadan | M37: Yes | P37: Married | Q37: Married | R37: ooluwatoba@cartafrica.org | S37: oluwatobang@yahoo.com | T37: +2348023451103 | U37: M.Sc. Cellular Parasitology, M.Sc Epidemiology | V37: 26284 | W37: Impact of environmental pollution on the prevalence of soil transmitted helminthes infection among primary school children in Ibadan | X37: Field | Y37: No | Z37: Primary | AA37: 17 | AB37: 40920 | AC37: 40969 | AE37: Dr. Roseangela Nwuba | AH37: =COUNTA(AE37:AG37) -> 1 | AI37: Home | AL37: Yes | AO37: Academic | AQ37: Lecturer | AT37: University of Ibadan | AU37: 0000-0003-1781-2550 | AW37: 40969 | AX37: 41214 | AY37: Yes | BF37: 41852 | BG37: Yes | BH37: 42064 | BI37: Yes | BM37: 43787 | BN37: Completed | BO37: =DATEDIF(AW37,BM37, "M")+1 -> 93 | BP37: =DATEDIF(AX37,BM37, "M")+1 -> 85 | BR37: 4 | BS37: 0 | BT37: 0 | BU37: 0 | BV37: 0 | BW37: 0 | BX37: 0 | BY37: No | BZ37: 0 | CE37: No | CH37: 3 | CI37: 3 | CK37: NF | CL37: Deceased 10/02/2023
A38: 39 | B38: C2/014 | C38: Peter | D38: Mpasho | E38: Mwamtobe | F38: Man | G38: 2 | H38: Malawi | I38: University of Malawi and Associates | J38: Disease Epidemiology | K38: MATHEMATICS AND STATISTICS | L38: University of Malawi and Associates | M38: Yes | P38: married | Q38: Married | R38: pmwamtobe@cartafrica.org | S38: pmwamtobe@gmail.com, pmwamtobe@poly.ac.mw | T38: 265999458069/265888626168 | U38: MSc in Mathematical Epidemiology (online) | V38: 27826 | W38: Optimal (control of) intervention strategies for malaria – TB co-infection | X38: Clinical research | Y38: yes | Z38: Primary | AA38: 8 | AB38: 41186 | AC38: 40969 | AE38: Prof. Ebrahim Momoniat | AF38: Prof. Shirley Abelman | AG38: Prof. Jean M. Tchuenche | AH38: =COUNTA(AE38:AG38) -> 3 | AI38: Other | AJ38: Other | AK38: Other | AL38: No | AM38: No | AN38: No | AO38: Academic | AP38: Lecturer | AQ38: Lecturer | AR38: No | AS38: Senior Lecturer, Head of Applied Studies Dept | AT38: UNIVERSITY OF MALAWI | AU38: 0000-0003-1861-3377 | AW38: 40969 | AX38: 41214 | AY38: Yes | BF38: 41852 | BG38: Yes | BH38: 42064 | BI38: Yes | BM38: 42064 | BN38: Completed | BO38: =DATEDIF(AW38,BM38, "M")+1 -> 37 | BP38: =DATEDIF(AX38,BM38, "M")+1 -> 29 | BR38: 0 | BS38: 2 | BT38: 6 | BU38: 1 | BV38: 0 | BW38: 1 | BX38: 0 | BY38: No | BZ38: 0 | CE38: No | CH38: 5 | CI38: 6 | CK38: NF
A39: 40 | B39: C2/015 | C39: Siphesihle | D39: Primrose Theodora | E39: Mtshali | F39: Woman | G39: 2 | H39: South Africa | I39: University of the Witwatersrand | J39: Kinesiology | K39: Department of Physiotherapy | L39: University of the Witwatersrand | M39: Yes | P39: NF | R39: pmtshali@cartafrica.org | S39: Siphe.mtshali@wits.ac.za | T39: +27723106078 | U39: M.Sc Physiotherapy | V39: 27470 | W39: Impact of an education programme on coaches’ knowledge, attitudes and practices on injury prevention amongst football players. | X39: Field | Y39: No | Z39: Primary | AA39: 15.5 | AB39: 40952 | AC39: 40969 | AD39: 45741 | AE39: Prof. Mbambo-Kekana Nonceba Priscilla | AF39: Dr. Hellen Myezwa | AG39: Dr. Kerith Aginsky | AH39: =COUNTA(AE39:AG39) -> 3 | AI39: Other | AJ39: Home | AK39: Home/ Host | AL39: Yes | AM39: Yes | AN39: Yes | AO39: Academic | AP39: Lecturer | AT39: NF | AU39: 0000-0002-8343-0342 | AW39: 40969 | AX39: 41214 | AY39: Yes | BF39: 41852 | BG39: Yes | BH39: 42064 | BI39: Yes | BN39: Terminated | BR39: 1 | BS39: 0 | BT39: 0 | BU39: 0 | BV39: 0 | BW39: 0 | BX39: 0 | BY39: No | BZ39: 0 | CE39: No | CH39: 1 | CI39: NF | CK39: NF
A40: 41 | B40: C2/016 | C40: Nalugo | D40: Scovia | E40: Mbalinda | F40: Woman | G40: 2 | H40: Uganda | I40: Makerere University | J40: Epidemiology | K40: Dept of Nursing | L40: Makerere University | M40: Yes | O40: Married | P40: Married | Q40: Married | R40: smbalinda@cartafrica.org | S40: snmbalinda@gmail.com, snmbalinda@chs.mak.ac.ug | T40: +256782212151 | U40: MSc. Population and Reproductive Health (online) | V40: 28657 | W40: Assessment of rural Ugandan HIV+ young adults women’s reproductive needs and rights to design a positive prevention service framework | X40: Field | Y40: No | Z40: Primary | AA40: 29 | AB40: 40867 | AC40: 40969 | AE40: Dr. Daniel Kabonge Kaye | AF40: Dr. Noah Kiwanuka | AG40: Prof. Fred Wabwire-Mangen | AH40: =COUNTA(AE40:AG40) -> 3 | AI40: Home | AJ40: Home | AK40: Home/ Host | AL40: Yes | AM40: No | AN40: No | AO40: Academic | AP40: Lecturer | AQ40: Lecturer | AR40: No | AT40: Makerere Univeristy | AU40: 0000-0002-4945-130X | AW40: 40969 | AX40: 41214 | AY40: Yes | BF40: 41852 | BG40: Yes | BH40: 42064 | BI40: Yes | BM40: 43108 | BN40: Completed | BO40: =DATEDIF(AW40,BM40, "M")+1 -> 71 | BP40: =DATEDIF(AX40,BM40, "M")+1 -> 63 | BR40: 6 | BS40: 20 | BT40: 18 | BU40: 5 | BV40: 0 | BW40: 0 | BX40: 0 | BY40: JAS 2, 2012 | BZ40: 0 | CE40: No | CH40: 3 | CI40: 3 | CK40: NF
A41: 42 | B41: C2/017 | C41: Nakubulwa | E41: Sarah | F41: Woman | G41: 2 | H41: Uganda | I41: Makerere University | J41: Obstertrics and reproductive health nursing | L41: Makerere University | M41: Yes | P41: NF | R41: snakubulwa@cartafrica.org | S41: sarahug@gmail.com | T41: +256772443416 | U41: M.Mc Obstetrics & Gynaecology | V41: 26892 | W41: Herpes Simplex Virus type 2 in pregnancy: Assessing the burden and associated factors in women with pre-labour rupture of membranes and exploring the effect of acyclovir on obstetric outcomes in this population in Mulago Clinical research. | X41: Clinical research | Y41: No | Z41: Primary | AA41: 19 | AB41: 40931 | AC41: 40969 | AE41: Dr. Nazarius Mbona Tumwesigye | AF41: Dr. Florence Mirembe | AG41: Dr. Daniel Kabonge Kaye | AH41: =COUNTA(AE41:AG41) -> 3 | AI41: Home | AJ41: Home | AK41: Home/ Host | AL41: Yes | AM41: No | AN41: Yes | AP41: Lecturer | AQ41: Senior Lecturer | AR41: Yes | AT41: Makerere Univeristy | AU41: 000 0002 1433 7312 | AW41: 40969 | AX41: 41214 | AY41: Yes | BF41: 41852 | BG41: Yes | BH41: 42064 | BI41: Yes | BM41: 42766 | BN41: Completed | BO41: =DATEDIF(AW41,BM41, "M")+1 -> 59 | BP41: =DATEDIF(AX41,BM41, "M")+1 -> 51 | BR41: NF | BS41: 2 | BT41: 0 | BU41: 1 | BV41: 0 | BW41: 0 | BX41: 0 | BY41: No | BZ41: 0 | CE41: No | CH41: NF | CI41: NF | CK41: NF
A42: 43 | B42: C2/018 | C42: Simbaharshe | E42: Takuva | F42: Man | G42: 2 | H42: South Africa | I42: University of the Witwatersrand | J42: Epidemiology | L42: University of the Witwatersrand | M42: Yes | P42: NF | R42: stakuva@cartafrica.org | T42: 27727577369 | U42: M.Sc Epidiomology | V42: 28270 | W42: Epidemiological Studies of Impact of Vitamin D Status and Vitamin D Gene Polymorphisms on HIV Disease Progression and Tuberculosis Susceptibility among HIV-infected Patients | X42: Clinical research | Y42: No | Z42: Primary | AA42: 1.5 | AB42: 40892 | AC42: 40969 | AD42: 45741 | AE42: Dr. Tobias Chirwa | AF42: Dr. Patrick MacPhail | AG42: Prof. Ian M. Sanne | AH42: =COUNTA(AE42:AG42) -> 3 | AI42: Home | AJ42: Home | AK42: Home/ Host | AL42: Yes | AM42: No | AN42: No | AO42: Researcher | AP42: Joint Faculty | AT42: UNIVERSITY OF THE WITWATERSRAND | AU42: 0000-0001-6030-2359 | AW42: 40969 | AX42: 41214 | AY42: Yes | BF42: 41852 | BG42: Yes | BH42: Not attended | BI42: No | BN42: Terminated | BR42: 1 | BS42: 31 | BT42: 0 | BU42: 7 | BV42: 3 | BW42: 0 | BX42: 0 | BY42: No | BZ42: 0 | CE42: No | CH42: NF | CI42: NF | CK42: NF
A43: 44 | B43: C2/019 | C43: Gloria | D43: Susan | E43: Omosa - Momanyi | F43: Woman | G43: 2 | H43: Kenya | I43: University of Nairobi | L43: University of the Witwatersrand | M43: No | N43: NF | O43: NF | P43: NF | Q43: NF | AA43: 4 | AC43: 40969 | AD43: 42662 | AH43: =COUNTA(AE43:AG43) -> 0 | AW43: 40969 | BN43: Terminated | BO43: Terminated | BY43: No | CK43: WT
A44: 45 | B44: C2/020 | C44: Phanuel | D44: Humphrey Jacob | E44: Shao | F44: Man | G44: 2 | H44: Tanzania | I44: Ifakara Health Institute | K44: TB Clinic | L44: University of Dar es Salaam | M44: No | N44: NF | O44: NF | P44: NF | Q44: NF | R44: hshao@cartafrica.org | S44: humphreyshao@gmail.com | AA44: 22.5 | AC44: 40969 | AD44: 42380 | AH44: =COUNTA(AE44:AG44) -> 0 | AW44: 40969 | BN44: Terminated | BO44: Terminated | BY44: No | CK44: NF
A45: 47 | B45: C3/001 | C45: Adefolarin | D45: Olufolake | E45: Adeyinka | F45: Woman | G45: 3 | H45: Nigeria | I45: University of Ibadan | J45: Health Promotion Professional | K45: Health Promotion and Education | L45: University of Ibadan | M45: Yes | N45: PGX12112012314129 | O45: Single | P45: Single | Q45: Single | R45: aadefolarin@cartafrica.org | S45: yinkuss2000@yahoo.com | T45: +2348033915930 | U45: Masters of Public Health (Health Promotion), Master of Social Work | V45: 26540 | W45: Maternal Mental Health and Fetal Outcome Among Pregnant Women Attending University College Clinical research Antenatal Clinic, Ibadan, Nigeria | X45: Clinical research | Y45: No | Z45: Primary | AA45: 17 | AB45: 41325 | AC45: 41334 | AE45: Oyedunni Arulogun | AF45: PROF Oye Gureje | AH45: =COUNTA(AE45:AG45) -> 2 | AI45: Home | AL45: Yes | AO45: Other | AP45: Principal Social Worker 1 | AQ45: Lecturer | AR45: Yes | AS45: Secretary of Ibadan Public Health Conference | AT45: UNIVERSITY OF IBADAN | AU45: 0000-0001-7238-2413 | AW45: 41334 | AX45: 41579 | AY45: Yes | AZ45: 41913 | BB45: 42153 | BE45: Effect of training and supervision on health talk delivery on maternal depression among primary health care workers in Ibadan, Nigeria | BF45: 42217 | BG45: Yes | BH45: 42428 | BI45: Yes | BJ45: 42976 | BK45: 43011 | BL45: 43038 | BM45: 43038 | BN45: Completed | BO45: =DATEDIF(AW45,BM45, "M")+1 -> 56 | BP45: =DATEDIF(AX45,BM45, "M")+1 -> 48 | BQ45: Effect of training and supervision on health talk delivery on maternal depression among primary health care workers in Ibadan, Nigeria | BR45: 0 | BS45: 0 | BT45: 5 | BU45: 2 | BV45: 0 | BW45: 0 | BX45: 0 | BY45: No | BZ45: 0 | CE45: No | CH45: 1 | CI45: 1 | CK45: WT
A46: 48 | B46: C3/002 | C46: Angeline | E46: Chepchirchir | F46: Woman | G46: 3 | H46: Kenya | I46: University of Nairobi | J46: Epidemiology | L46: University of Nairobi | M46: Yes | O46: Married | P46: married | Q46: Married | R46: achepchirchir@cartafrica.org | S46: chepchirchir@uonbi.ac.ke | T46: 254720440665 | U46: NF | V46: 27702 | W46: Determination of the Pathogen burden and individual variability in immune response: a comparative study of non-hypertensive and hypertensive subjects at Kenyatta National Clinical research. | X46: Clinical research | Y46: yes | Z46: Primary | AA46: 18.5 | AB46: 41329 | AC46: 41334 | AE46: Prof. Nyagol Akelo Joshua | AF46: Prof. Jaoko Walter | AH46: =COUNTA(AE46:AG46) -> 2 | AI46: Home | AL46: Yes | AO46: Academic | AQ46: Lecturer | AR46: Yes | AT46: UNIVERSITY OF NAIROBI | AU46: 0000-0002-4033-7869 | AW46: 41334 | AX46: 41579 | AY46: Yes | BF46: 42217 | BG46: Yes | BH46: 42428 | BI46: Yes | BM46: 43819 | BN46: Completed | BO46: =DATEDIF(AW46,BM46, "M")+1 -> 82 | BP46: =DATEDIF(AX46,BM46, "M")+1 -> 74 | BR46: 2 | BS46: 1 | BT46: 1 | BU46: 0 | BV46: 0 | BW46: 0 | BX46: 0 | BY46: No | BZ46: 0 | CE46: No | CH46: 1 | CI46: 4 | CK46: WT
A47: 49 | B47: C3/003 | C47: Anne | D47: Majuma | E47: Khisa | F47: Woman | G47: 3 | H47: Kenya | I47: University of Nairobi | J47: Obstertrics and reproductive health nursing | K47: Reseach Capacity Strengtheniing Division | L47: University of Nairobi | M47: Yes | N47: H80/83881/2012 | O47: Single | P47: Single | R47: akhisa@cartafrica.org | S47: annekhisa@gmail.com | T47: +254 724 348 661 | U47: MA in Gender and Development Studies | V47: 30620 | W47: Health Seeking Behaviour and Reintegration of Patients with Obstetric Fistula in Kenya | X47: Field | Y47: No | Z47: Primary | AA47: 6.5 | AB47: 41097 | AC47: 41334 | AE47: Grace Omoni | AF47: Prof Isaac Nyamongo | AG47: Dr Sabina Wakasiaka | AH47: =COUNTA(AE47:AG47) -> 3 | AI47: Home | AJ47: Home | AK47: Home | AL47: Yes | AM47: No | AN47: No | AO47: Other | AP47: Part Time Lecturer | AQ47: Post Doc Research Fellow | AR47: Yes | AU47: 0000-0001-6110-0118 | AW47: 41334 | AX47: 41579 | AY47: Yes | BE47: A grounded theory of regaining normalcy: Health seeking behaviour and reintegration of patients with obstetric fistula in Kenya | BF47: 42217 | BG47: Yes | BH47: 42428 | BI47: Yes | BM47: 42735 | BN47: Completed | BO47: =DATEDIF(AW47,BM47, "M")+1 -> 46 | BP47: =DATEDIF(AX47,BM47, "M")+1 -> 38 | BQ47: A grounded theory of regaining normalcy: Health seeking behaviour and reintegration of patients with obstetric fistula in Kenya | BR47: 1 | BS47: 1 | BT47: 4 | BU47: 1 | BV47: 0 | BW47: 0 | BX47: 0 | BY47: No | BZ47: 0 | CE47: No | CH47: 0 | CI47: 0 | CK47: WT
A48: 50 | B48: C3/004 | C48: Adesola | D48: Oluwafunmilola | E48: Olumide | F48: Woman | G48: 3 | H48: Nigeria | I48: University of Ibadan | J48: Adolescent health | K48: Institute of Child health | L48: University of Ibadan | M48: Yes | O48: Single | P48: Single | R48: asangowawa@cartafrica.org | S48: daisyolu@yahoo.com | T48: +2348033265796 | U48: MPH | V48: 26913 | W48: Epidemiology and Costs of Injuries Among Adolescents in Ibadan, South-Western Nigeria | X48: Field | Y48: No | Z48: Primary | AA48: 6.5 | AB48: 41326 | AC48: 41334 | AE48: Olayemi Omotade | AH48: =COUNTA(AE48:AG48) -> 1 | AI48: Home | AL48: Yes | AO48: Academic | AP48: Senior Research Fellow | AQ48: Senior Medical Research Fellow | AR48: No | AS48: Head and Actg director Institute of Child Health | AT48: UNIVERSITY OF IBADAN | AU48: 0000-0003-4372-9822 | AW48: 41334 | AX48: 41579 | AY48: Yes | BF48: 42217 | BG48: Yes | BH48: 42428 | BI48: Yes | BM48: 42916 | BN48: Completed | BO48: =DATEDIF(AW48,BM48, "M")+1 -> 52 | BP48: =DATEDIF(AX48,BM48, "M")+1 -> 44 | BR48: 0 | BS48: 18 | BT48: 17 | BU48: 11 | BV48: 1 | BW48: 0 | BX48: 0 | BY48: No | BZ48: 0 | CE48: No | CH48: 0 | CI48: 0 | CK48: MAC
A49: 51 | B49: C3/005 | C49: Kato | D49: Charles | E49: Drago | F49: Man | G49: 3 | H49: Uganda | I49: Makerere University | J49: Immunity and Infection | L49: Makerere University | M49: Yes | O49: Married | P49: Married | Q49: Married | R49: ckato@cartafrica.org | S49: katodrago@yahoo.com | T49: +256712959954 | U49: MSc. Structural Molecular Biology | V49: 29083 | W49: Cytokine responses & parasite genotypes associated with the pathogenesis of human African trypanosomiasis (HAT) in north-eastern Uganda | X49: Experimental model | Y49: yes | Z49: Primary | AA49: 18.5 | AB49: 41163 | AC49: 41334 | AE49: Prof. Matovu Enock | AF49: Dr. Vincent Pius Alibu | AH49: =COUNTA(AE49:AG49) -> 2 | AI49: Home | AL49: Yes | AO49: Academic | AP49: Assistant Lecturer | AQ49: Lecturer | AR49: Yes | AT49: MAKERERE UNIVERISTY | AU49: 0000-0003-3160-6657 | AW49: 41334 | AX49: 41579 | AY49: Yes | BF49: 42217 | BG49: Yes | BH49: 42428 | BI49: Yes | BM49: 42460 | BN49: Completed | BO49: =DATEDIF(AW49,BM49, "M")+1 -> 37 | BP49: =DATEDIF(AX49,BM49, "M")+1 -> 29 | BR49: 0 | BS49: 6 | BT49: 31 | BU49: 0 | BV49: 1 | BW49: 0 | BX49: 0 | BY49: No | BZ49: 0 | CE49: No | CH49: 1 | CI49: 2 | CK49: SIDA
A50: 52 | B50: C3/006 | C50: Charles | D50: Masulani | E50: Mwale | F50: Man | G50: 3 | H50: Rwanda | I50: University of Rwanda | J50: Public Health | L50: University of Rwanda | M50: Yes | P50: NF | R50: cmwale@cartafrica.org | S50: cmmwale@hotmail.com | T50: +265999927938 | U50: Master of Public Health | V50: 28395 | W50: A cross-sectional study on the mental health service delivery for people living with AIDS (PLWAs) in Malawi | X50: Field | Y50: No | Z50: Primary | AA50: 15 | AB50: 41200 | AC50: 41334 | AE50: Pascal Mathanga | AH50: =COUNTA(AE50:AG50) -> 1 | AI50: Home | AL50: Yes | AO50: Academic | AP50: Part Time Senior Lecturer | AQ50: Part Time Senior Lecturer | AR50: No | AT50: UNIVERSITY OF MALAWI | AU50: 0000-0001-8676-1713 | AW50: 41334 | AX50: 41579 | AY50: Yes | BE50: A mixed methods study on designing and testing effectiveness of a psychosocial training intervention (Titukulane) in improving psychological wellbeing of parents for intellectually disabled children in Malawi | BF50: 42217 | BG50: Yes | BH50: 42428 | BI50: Yes | BM50: 43069 | BN50: Completed | BO50: =DATEDIF(AW50,BM50, "M")+1 -> 57 | BP50: =DATEDIF(AX50,BM50, "M")+1 -> 49 | BQ50: A mixed methods study on designing and testing effectiveness of a psychosocial training intervention (Titukulane) in improving psychological wellbeing of parents for intellectually disabled children in Malawi | BR50: 0 | BS50: 3 | BT50: 3 | BU50: 2 | BV50: 0 | BW50: 0 | BX50: 0 | BY50: No | BZ50: 0 | CE50: No | CH50: NF | CI50: NF | CK50: WT
A51: 53 | B51: C3/007 | C51: Olusegun | D51: Emmanuel | E51: Thomas | F51: Man | G51: 3 | H51: Nigeria | I51: University of Ibadan | J51: Pharmaceutical Sciences | K51: Pharmaceutical Chemistry | L51: University of Ibadan | M51: Yes | N51: 95534 | O51: Married | P51: Married | Q51: Married | R51: tolusegun@cartafrica.org | S51: seguntom@yahoo.com | T51: +2348034198737 | U51: MSc. Pharmaceutical Chemistry and Drug Analysis | V51: 28708 | W51: Design, synthesis and genotoxicity evaluation of non-toxic azo dyes based on tetracyclic structures | X51: Experimental model | Y51: yes | Z51: Primary | AA51: 14.5 | AB51: 41004 | AC51: 41334 | AE51: Prof. Adegoke Aremu Olajire | AH51: =COUNTA(AE51:AG51) -> 1 | AI51: Home | AL51: Yes | AO51: Academic | AP51: Lecturer | AQ51: Senior Lecturer | AR51: Yes | AT51: UNIVERSITY OF IBADAN | AU51: 0000-0001-8519-2125 | AW51: 41334 | AX51: 41579 | AY51: Yes | BF51: 42217 | BG51: Yes | BH51: 42794 | BI51: No | BM51: 42978 | BN51: Completed | BO51: =DATEDIF(AW51,BM51, "M")+1 -> 54 | BP51: =DATEDIF(AX51,BM51, "M")+1 -> 46 | BR51: 0 | BS51: 3 | BT51: 4 | BU51: 2 | BV51: 0 | BW51: 0 | BX51: 0 | BY51: No | BZ51: 0 | CE51: No | CI51: 1 | CK51: MAC
A52: 54 | B52: C3/008 | C52: Tonney | D52: Stophen | E52: Nyirenda | F52: Man | G52: 3 | H52: Malawi | I52: University of Malawi and Associates | J52: Immunity and Infection | K52: Pathology | L52: University of Malawi and Associates | M52: Yes | P52: Married | R52: tnyirenda@cartafrica.org | S52: tnyirenda@medcol.mw | T52: +265995573845 | U52: MSc. Immunology | V52: 29697 | W52: Development of adaptive immunity to non-typhoidal Salmonella in Children | X52: Field | Y52: yes | Z52: Primary | AA52: 10.5 | AB52: 40848 | AC52: 41334 | AE52: Wilson Mandala | AH52: =COUNTA(AE52:AG52) -> 1 | AI52: Home | AL52: Yes | AO52: Academic | AP52: PhD Student | AQ52: Lecturer | AR52: Yes | AT52: UNIVERSITY OF MALAWI | AU52: 0000-0002-4874-9518 | AW52: 41334 | AX52: 41579 | AY52: Yes | BF52: 42217 | BG52: Yes | BH52: 42428 | BI52: Yes | BM52: 42173 | BN52: Completed | BO52: =DATEDIF(AW52,BM52, "M")+1 -> 28 | BP52: =DATEDIF(AX52,BM52, "M")+1 -> 20 | BR52: 1 | BS52: 1 | BT52: 15 | BU52: 2 | BV52: 0 | BW52: 2 | BX52: 0 | BY52: No | BZ52: 0 | CE52: No | CH52: NF | CI52: NF | CK52: SIDA
A53: 55 | B53: C3/009 | C53: Evangeline | D53: Wawira | E53: Njiru | F53: Woman | G53: 3 | H53: Kenya | I53: Moi University | J53: MEDICAL ANTHROPOLOGY | K53: ANTHROPOLOGY AND HUMAN ECOLOGY | L53: Moi University | M53: Yes | N53: SASS/DPHIL/ANT/02/12 | O53: Married | P53: Separated | R53: enjiru@cartafrica.org | S53: oyungueva@yahoo.com | T53: +254-722-624-353 | U53: Masters in Medicine | V53: 26750 | W53: Situational analysis of cancer care in the Western Kenya population | X53: Field | Y53: No | Z53: Primary | AA53: 15 | AB53: 41153 | AC53: 41334 | AE53: Jamin Masinde | AF53: Dr. Harrison Maithya | AH53: =COUNTA(AE53:AG53) -> 2 | AI53: Home | AJ53: Home | AL53: Yes | AM53: Yes | AO53: Academic | AP53: Lecturer | AT53: MOI UNIVERSITY | AU53: 0000-0002-0064-8777 | AW53: 41334 | AX53: 41579 | AY53: Yes | BF53: 42585 | BG53: No | BH53: 42793 | BI53: No | BN53: In progress | BR53: 0 | BS53: 7 | BT53: 0 | BU53: 0 | BV53: 0 | BW53: 0 | BX53: 0 | BY53: No | BZ53: 0 | CE53: No | CH53: 3 | CI53: NF | CK53: SIDA
A54: 56 | B54: C3/010 | C54: Samanta | D54: Tresha | E54: Lalla-Edward | F54: Woman | G54: 3 | H54: South Africa | I54: University of the Witwatersrand | J54: Public Health | K54: Wits Reproductive Health and HIV Institute | L54: University of the Witwatersrand | M54: Yes | N54: 705854 | P54: Married | R54: esamanta@cartafrica.org | S54: slallaedward@ezintsha.org; | T54: 113585404 | U54: Masters in Social Behaviour Studies in HIV/AIDS | V54: 29258 | W54: The effect of combination HIV prevention interventions: a comparison between men who have sex with men (MSM) sex workers and MSM non-sex workers | X54: Field | Y54: No | Z54: Primary | AA54: 8.5 | AB54: 41548 | AC54: 41334 | AE54: Maria Elizabeth Rabe | AH54: =COUNTA(AE54:AG54) -> 1 | AI54: Other | AL54: No | AO54: Other | AP54: M&E Technical Specialist - Wits | AQ54: Program Manager | AR54: Yes | AT54: EZINTSHA, SOUTH AFRICA (2021) | AU54: 0000-0003-3597-1643 | AW54: 41334 | AX54: 41579 | AY54: Yes | BE54: A process evaluation of newly implementing South African Roadside wellness clinics for truck drivers | BF54: 42217 | BG54: Yes | BH54: 42428 | BI54: Yes | BM54: 43291 | BN54: Completed | BO54: =DATEDIF(AW54,BM54, "M")+1 -> 65 | BP54: =DATEDIF(AX54,BM54, "M")+1 -> 57 | BQ54: A process evaluation of newly implementing South African Roadside wellness clinics for truck drivers | BR54: 0 | BS54: 5 | BT54: 31 | BU54: 1 | BV54: 0 | BW54: 0 | BX54: 0 | BY54: No | BZ54: 0 | CE54: No | CH54: 1 | CI54: 2 | CK54: FF
A55: 57 | B55: C3/011 | C55: Emmanuel | E55: Shema | F55: Man | G55: 3 | H55: Rwanda | I55: University of Rwanda | J55: Demography | L55: Moi University | M55: No | N55: EDU/D.Phil/CM/1010/16 | O55: Married | P55: Married | R55: esebahutu@cartafrica.org | S55: esebahutu@nur.ac.rw sebem01@yahoo.fr | T55: 250788647761 | U55: Masters in Social Educational research Methods | V55: 27997 | W55: Building Awareness of both Men and Women through Formal Education with regard to Women’s Sexual and Reproductive Rights towards the Reduction of Fertility Rates in Rwanda: Challenges and Future Trends. | X55: Field | Y55: No | Z55: Primary | AA55: 17.5 | AB55: 41360 | AC55: 41334 | AE55: Prof Mukwa Wekesa Christopher | AF55: Dr. Wanyonyi Wamamili David | AH55: =COUNTA(AE55:AG55) -> 2 | AI55: Host | AL55: Yes | AO55: Academic | AP55: Assistant Lecturer | AQ55: Assistant Lecturer | AR55: No | AT55: UNIVERSITY OF RWANDA | AW55: 41334 | AX55: 41579 | AY55: Yes | AZ55: 42860 | BA55: 42860 | BE55: Factors Associated with the Integration of Internet in Teaching Comprehensive Sexuality Education in Southern Province, Rwanda | BF55: 42948 | BG55: No | BH55: 43164 | BI55: No | BN55: In progress | BR55: 0 | BS55: 0 | BT55: 0 | BU55: 0 | BV55: 0 | BW55: 0 | BX55: 0 | BY55: No | BZ55: 0 | CE55: No | CH55: 4 | CI55: 5 | CK55: FF
A56: 58 | B56: C3/012 | C56: Fredrick | D56: Okoth | E56: Okaka | F56: Man | G56: 3 | H56: Kenya | I56: Moi University | J56: Human Geography | K56: Geography | L56: Moi University | M56: Yes | N56: SASS/GEO/DPHIL/01/12 | O56: Married | P56: Married | Q56: Married | R56: fokaka@cartafrica.org | S56: fredrickokaka@yaoo.com fredrickokaka@gmail.com | T56: +254 722 260034 | U56: Masters of Art (Settlement Geography) | V56: 26787 | W56: Urban Residents’ Perception of Climate Change as a Human Health Risk in Kenya: The Case of Kisumu and Mombasa Urban Centers | X56: Field | Y56: No | Z56: Primary | AA56: 22.5 | AB56: 41130 | AC56: 41334 | AE56: Prof. Paul Omondi | AF56: Prof. Beneah D. O. Odhiambo | AH56: =COUNTA(AE56:AG56) -> 2 | AI56: Home | AL56: Yes | AO56: Academic | AP56: Assistant Lecturer | AQ56: Senior Lecturer | AR56: Yes | AT56: MOI UNIVERSITY | AU56: 0000-0002-7140-0306 | AW56: 41334 | AX56: 41579 | AY56: Yes | AZ56: 41802 | BB56: 41960 | BE56: Urban residents' perception and adaptive capacity and behaviour to the health risks of climate change in Mombasa city, Kenya | BF56: 42217 | BG56: Yes | BH56: 42428 | BI56: Yes | BJ56: 42522 | BK56: 42660 | BL56: 42678 | BM56: 42678 | BN56: Completed | BO56: =DATEDIF(AW56,BM56, "M")+1 -> 45 | BP56: =DATEDIF(AX56,BM56, "M")+1 -> 37 | BQ56: Urban residents' perception and adaptive capacity and behaviour to the health risks of climate change in Mombasa city, Kenya | BR56: 0 | BS56: 1 | BT56: 4 | BU56: 0 | BV56: 0 | BW56: 2 | BX56: 0 | BY56: No | BZ56: 0 | CE56: No | CH56: 3 | CI56: 3 | CK56: WT
A57: 59 | B57: C3/013 | C57: Joel | D57: Olayiwola | E57: Faronbi | F57: Man | G57: 3 | H57: Nigeria | I57: Obafemi Awolowo University | J57: Epidemiology | L57: Obafemi Awolowo University | M57: Yes | O57: Married | P57: Married | Q57: Married | R57: jfaronbi@cartafrica.org | S57: faronbiy2k@yahoh.co.uk | T57: +2348033383018 | U57: MSC Nursing | V57: 26608 | W57: Impact of Nurse Moderated Intervention on the Quality of Life, Burden and Coping Strategies of Caregivers of the Elderly with Chronic Illness. | X57: Field | Y57: No | Z57: Primary | AA57: 20 | AB57: 41178 | AC57: 41334 | AE57: Olaogun Adenike Ayobola | AH57: =COUNTA(AE57:AG57) -> 1 | AI57: Home | AL57: Yes | AO57: Academic | AP57: Lecturer II | AQ57: Senior Lecturer | AR57: Yes | AS57: Department Postgraduate programme cordinator | AT57: OBAFEMI AWOLOWO UNIVERSITY | AU57: 0000-0003-3392-4472 | AW57: 41334 | AX57: 41579 | AY57: Yes | AZ57: 41506 | BB57: 43403 | BE57: Burden, coping strategies and health related quality of life of caregivers of elderly with chronic illness in Osun State, Nigeria | BF57: 42217 | BG57: Yes | BH57: 42428 | BI57: Yes | BJ57: 42205 | BK57: 42231 | BL57: 42258 | BM57: 42350 | BN57: Completed | BO57: =DATEDIF(AW57,BM57, "M")+1 -> 34 | BP57: =DATEDIF(AX57,BM57, "M")+1 -> 26 | BQ57: Burden, coping strategies and health related quality of life of caregivers of elderly with chronic illness in Osun State, Nigeria | BR57: 3 | BS57: 1 | BT57: 13 | BU57: 2 | BV57: 0 | BW57: 3 | BX57: 0 | BY57: No | BZ57: 0 | CE57: No | CH57: 2 | CI57: 3 | CK57: WT
A58: 60 | B58: C3/014 | C58: Judith | D58: Nekesa | E58: Mangeni | F58: Woman | G58: 3 | H58: Kenya | I58: Moi University | J58: Epidemiology | K58: Epidemiology and Biostatistics | L58: University of Nairobi | M58: No | N58: H80/92321/2013 | O58: Married | P58: Married | Q58: Married | R58: jmangeni@cartafrica.org | S58: nakholi2001@yahoo.com | T58: +254-722-647-415 | U58: MPH (Epidemiology and Disease control tract | V58: 28293 | W58: Motivational Interventions in community hypertension screening in western Kenya | X58: Field | Y58: No | Z58: Primary | AA58: 3.5 | AB58: 41432 | AC58: 41334 | AE58: Anne Wanjiru Mwangi | AH58: =COUNTA(AE58:AG58) -> 1 | AI58: Home | AL58: Yes | AO58: Academic | AP58: Assistant Lecturer | AQ58: Lecturer | AR58: Yes | AS58: Head ISO Quality Management system | AT58: MOI UNIVERSITY | AU58: 0000-0001-7333-9329 | AW58: 41334 | AX58: 41579 | AY58: Yes | BF58: 42217 | BG58: Yes | BH58: 42428 | BI58: Yes | BM58: 42855 | BN58: Completed | BO58: =DATEDIF(AW58,BM58, "M")+1 -> 50 | BP58: =DATEDIF(AX58,BM58, "M")+1 -> 42 | BR58: 3 | BS58: 3 | BT58: 10 | BU58: 4 | BV58: 1 | BW58: 0 | BX58: 0 | BY58: No | BZ58: 0 | CE58: No | CH58: 3 | CI58: 3 | CK58: SIDA
A59: 61 | B59: C3/015 | C59: Ojo | D59: Melvin | E59: Agunbiade | F59: Man | G59: 3 | H59: Nigeria | I59: Obafemi Awolowo University | J59: Sociology | K59: Sociology | L59: University of the Witwatersrand | M59: No | N59: 671975 | O59: Married | P59: Married | Q59: Married | R59: magunbiade@cartafrica.org | S59: ojomelvin@yahoo.com ojomelvin@gmail.com | T59: +2348059221715 | U59: MSC Sociology and Anthropology (Medical Sociology option) | V59: 27857 | W59: Attitudes towards Sexuality in Later Life among Yoruba People in Southwestern Nigeria | X59: Field | Y59: No | Z59: Primary | AA59: 11.5 | AB59: 41330 | AC59: 41334 | AE59: Emeritus Professor Gilbert Leah | AH59: =COUNTA(AE59:AG59) -> 1 | AI59: Host | AL59: No | AO59: Academic | AP59: Lecturer II | AQ59: Professor | AR59: Yes | AS59: Co-ordinator the University wide research methodology for all doctoral candidates at OAU | AT59: OBAFEMI AWOLOWO UNIVERSITY | AU59: 0000-0001-8566-0662 | AW59: 41337 | AX59: 41579 | AY59: Yes | AZ59: 41485 | BB59: 41607 | BF59: 42227 | BG59: Yes | BH59: 42429 | BI59: Yes | BJ59: 42429 | BK59: 42559 | BL59: 42618 | BM59: 42620 | BN59: Completed | BO59: =DATEDIF(AW59,BM59, "M")+1 -> 43 | BP59: =DATEDIF(AX59,BM59, "M")+1 -> 35 | BQ59: Socio-cultural constructions of Sexuality and help-seeking behaviour among eldeerly Yoruba people in Urban Ibadan, SouthWest Nigeria | BR59: 9 | BS59: 5 | BT59: 10 | BU59: 4 | BV59: 2 | BW59: 2 | BX59: 1 | BY59: No | BZ59: 0 | CE59: No | CH59: 1 | CI59: 3 | CK59: FF
A60: 62 | B60: C3/016 | C60: Marjorie | D60: Kyomuhendo | E60: Niyitegeka | F60: Woman | G60: 3 | H60: Uganda | I60: Makerere University | J60: Public Health | K60: Department of Journalism and Communication | L60: Makerere University | M60: Yes | O60: Married | P60: Married | Q60: Married | R60: mkyomuhendo@cartafrica.org | S60: marjorie@masscom.mak.ac.ug marjkyom@gmail.com | T60: +256776672000/256772672300 | U60: Master of Philosophy (media studies) | V60: 28469 | W60: Awareness to practice: Improving the Effectiveness of Family Planning Communication in Uganda | X60: Field | Y60: No | Z60: Primary | AA60: 20.5 | AB60: 41325 | AC60: 41334 | AE60: Monica Chibita | AF60: Fred Ntoni Nuwaha | AH60: =COUNTA(AE60:AG60) -> 2 | AI60: Other | AJ60: Home | AL60: No | AO60: Administrative | AP60: Assistant Lecturer | AT60: MAKERERE UNIVERSITY | AW60: 41334 | AX60: 41579 | AY60: Yes | BF60: 42217 | BG60: Yes | BH60: 42428 | BI60: Yes | BK60: 44578 | BM60: 44578 | BN60: Completed | BO60: =DATEDIF(AW60,BM60, "M")+1 -> 107 | BP60: =DATEDIF(AX60,BM60, "M")+1 -> 99 | BQ60: Family planning communication in Uganda: An interrogation of media reporting, communication campaigns and audience perspectives | BR60: 0 | BS60: 0 | BT60: 0 | BU60: 0 | BV60: 0 | BW60: 0 | BX60: 0 | BY60: No | BZ60: 0 | CE60: No | CH60: 2 | CI60: 2 | CK60: WT
A61: 63 | B61: C3/017 | C61: Nicolette | D61: Prea | E61: Naidoo | F61: Woman | G61: 3 | H61: South Africa | I61: University of the Witwatersrand | J61: Public Health | L61: University of the Witwatersrand | M61: Yes | P61: NF | R61: nnaidoo@cartafrica.org | S61: nnaidoo@wrhi.ac.za | T61: 0824901214 | U61: MPH (Health Management) | V61: 29865 | W61: An individually randomised multisite controlled trial of a comprehensive mobile phone intervention compared to the standard of care for improving adherence and retention outcomes in adult patients accessing HIV testing and treatment services in the inner city of Johannesburg, South Africa. | X61: Field | Y61: No | Z61: Primary | AA61: 4 | AB61: 41345 | AC61: 41334 | AD61: 45741 | AE61: Sinead-Delany Moretlwe | AF61: Prof Alain Labrique | AH61: =COUNTA(AE61:AG61) -> 2 | AI61: Home | AJ61: Other | AL61: Yes | AM61: No | AO61: Academic | AP61: Researcher | AT61: UNIVERSITY OF THE WITWATERSRAND | AU61: 0000-0002-7197-9426 | AW61: 41334 | AX61: 41579 | AY61: Yes | BF61: 42217 | BG61: Yes | BH61: 42428 | BI61: Yes | BN61: Terminated | BR61: 1 | BS61: 13 | BT61: 0 | BU61: 0 | BV61: 0 | BW61: 0 | BX61: 0 | BY61: No | BZ61: 0 | CE61: No | CH61: NF | CI61: NF | CK61: NF
A62: 64 | B62: C3/018 | C62: Olufunmilayo | D62: Olufunmilola | E62: Banjo | F62: Woman | G62: 3 | H62: Nigeria | I62: Obafemi Awolowo University | J62: Demography | K62: Demography & Social Statistics | L62: Obafemi Awolowo University | M62: Yes | N62: SSP/08/09/H/1290 | O62: Married | P62: Married | Q62: Married | R62: obanjo@cartafrica.org | S62: banjoolufunmilayo@gmail.com | T62: +2348034962623 | U62: MSc. Demography and Social Statistics | V62: 27926 | W62: Women status and fertility in sub Saharan Africa. | X62: Field | Y62: No | Z62: Secondary | AA62: 19.5 | AB62: 41304 | AC62: 41334 | AE62: Bisiriyu Adeleke Luqman | AF62: Dr. BAMIWUYE, Samson Olusina | AH62: =COUNTA(AE62:AG62) -> 2 | AI62: Home | AJ62: Home | AL62: Yes | AM62: Yes | AO62: Academic | AP62: Lecturer II | AQ62: Professor | AR62: Yes | AS62: Acting Director, Centre for Gender and Social policy | AT62: OBAFEMI AWOLOWO UNIVERSITY | AU62: 0000-0001-6433-9300 | AW62: 41334 | AX62: 41579 | AY62: Yes | BF62: 42217 | BG62: Yes | BH62: 42428 | BI62: Yes | BM62: 42151 | BN62: Completed | BO62: =DATEDIF(AW62,BM62, "M")+1 -> 27 | BP62: =DATEDIF(AX62,BM62, "M")+1 -> 19 | BR62: 1 | BS62: 0 | BT62: 12 | BU62: 0 | BV62: 0 | BW62: 1 | BX62: 1 | BY62: JAS 1, 2013 | BZ62: 0 | CE62: No | CH62: 5 | CI62: 5 | CK62: WT
A63: 65 | B63: C3/019 | C63: Obasola | D63: Ireti | E63: Oluwaseun | F63: Woman | G63: 3 | H63: Nigeria | I63: University of Ibadan | J63: Public Health | L63: University of Ibadan | M63: Yes | O63: Married | P63: Married | Q63: Married | R63: oobasola@cartafrica.org | S63: olaseun@yahoo.com | T63: +2348033517020 | U63: Master of Library Science, Archival and information Studies | V63: 28167 | W63: Impact of ICT Utilization in the Provision of Health Information on Maternal and Child Health in Nigeria. | X63: Field | Y63: No | Z63: Primary | AA63: 15 | AB63: 41178 | AC63: 41334 | AE63: Iyabo Mabawonku | AH63: =COUNTA(AE63:AG63) -> 1 | AI63: Home | AL63: Yes | AO63: Academic | AP63: Librarian II | AQ63: Senior Librarian | AR63: Yes | AT63: UNIVERSITY OF IBADAN TO 2020 INTERNATIONAL ATOMIC ENERGY AGENCY | AU63: 0000-0001-8164-3953 | AW63: 41337 | AX63: 41596 | AY63: Yes | AZ63: 41883 | BB63: 42040 | BF63: 42217 | BG63: Yes | BH63: 42429 | BI63: Yes | BK63: 27/5/2015 | BL63: 42957 | BM63: 42825 | BN63: Completed | BO63: =DATEDIF(AW63,BM63, "M")+1 -> 49 | BP63: =DATEDIF(AX63,BM63, "M")+1 -> 41 | BQ63: Mothers’ Perception of ICT use by Health Workers and Disseminated Information on Maternal Health Practices in Nigeria | BR63: 1 | BS63: 3 | BT63: 6 | BU63: 3 | BV63: 0 | BW63: 0 | BX63: 0 | BY63: No | BZ63: 0 | CE63: No | CH63: 3 | CI63: 3 | CK63: SIDA
A64: 66 | B64: C3/020 | C64: Anitha | D64: - | E64: Philbert | F64: Woman | G64: 3 | H64: Tanzania | I64: University of Dar es Salaam | J64: Zoology/Ecology | K64: Zoology and Wildlife Conservation | L64: University of Dar es Salaam | M64: Yes | N64: 2012-04-00184 | O64: Married | P64: Married | Q64: Married | R64: panitha@cartafrica.org | S64: annybyabato@yahoo.com | T64: +255784454541 | U64: MSC. Applied Zoology | V64: 29476 | W64: Causes and Consequences of Insecticide Resistance in Malaria Vectors. A Case Study of Dar es Salaam, Tanzania | X64: Experimental model | Y64: yes | Z64: Primary | AA64: 19.5 | AB64: 41205 | AC64: 40969 | AE64: Nkwengulila Gamba | AF64: DR SYLVESTER LYANTAGAYE | AH64: =COUNTA(AE64:AG64) -> 2 | AI64: Home | AJ64: Home | AL64: Yes | AM64: No | AO64: Academic | AP64: Assistant Lecturer | AQ64: Senior Lecturer | AR64: Yes | AT64: UNIVERSITY OF DAR ES SALAAM | AU64: 0000-0002-0301-2272 | AW64: 41334 | AX64: 41579 | AY64: Yes | AZ64: 41432 | BB64: 41590 | BE64: Insecticide resistance in malaria vectors: seasonal susceptibility mechanisms and relationships to agricultural practices in Magu and Sengerema Agro-Ecosystem Zone | BF64: 42217 | BG64: Yes | BH64: 42428 | BI64: Yes | BJ64: 42260 | BK64: 42565 | BL64: 42612 | BM64: 42612 | BN64: Completed | BO64: =DATEDIF(AW64,BM64, "M")+1 -> 42 | BP64: =DATEDIF(AX64,BM64, "M")+1 -> 34 | BQ64: Insecticide resistance in malaria vectors: seasonal susceptibility mechanisms and relationships to agricultural practices in Magu and Sengerema Agro-Ecosystem Zone | BR64: 0 | BS64: 0 | BT64: 8 | BU64: 2 | BV64: 0 | BW64: 0 | BX64: 0 | BY64: No | BZ64: 0 | CE64: No | CH64: 2 | CI64: 2 | CJ64: 1 by thesis | CK64: WT
A65: 68 | B65: C3/022 | C65: Save | E65: Kumwenda | F65: Man | G65: 3 | H65: Malawi | I65: University of Malawi and Associates | J65: Public Health | K65: Public Health | L65: University of Malawi and Associates | M65: Yes | N65: 201380012518 | P65: Married | Q65: Married | R65: skumwenda@cartafrica.org | S65: skumwenda@gmail.com | T65: +265888389452 | U65: Master of Public Health | V65: 28167 | W65: Comparative analysis of determinants of access to good maternal health care services | X65: Field | Y65: yes | Z65: Primary | AA65: 8.5 | AB65: 41579 | AC65: 41334 | AE65: Dr. Chisomo Msefula | AF65: Dr. Bagrey Ngwira | AH65: =COUNTA(AE65:AG65) -> 2 | AI65: Home | AJ65: Home | AL65: No | AM65: No | AO65: Academic | AP65: Lecturer | AQ65: Associate Professor | AR65: Yes | AT65: UNIVERSITY OF MALAWI | AU65: 0000-0002-3329-5875 | AW65: 41334 | AX65: 41579 | AY65: Yes | AZ65: 41415 | BA65: 41700 | BE65: Pathogen survival in Ecosan latrines and the associated health risks | BF65: 42217 | BG65: Yes | BH65: 42428 | BI65: Yes | BM65: 43568 | BN65: Completed | BO65: =DATEDIF(AW65,BM65, "M")+1 -> 74 | BP65: =DATEDIF(AX65,BM65, "M")+1 -> 66 | BR65: 1 | BS65: 16 | BT65: 5 | BU65: 5 | BV65: 1 | BW65: 0 | BX65: 0 | BY65: No | BZ65: 0 | CE65: No | CH65: 1 | CI65: 3 | CK65: SIDA
A66: 70 | B66: C3/024 | C66: Steven | E66: Pentz | F66: Man | G66: 3 | H66: South Africa | I66: University of the Witwatersrand | L66: University of the Witwatersrand | M66: No | N66: NF | O66: NF | P66: NF | Q66: NF | AC66: 41334 | AD66: 42004 | AH66: =COUNTA(AE66:AG66) -> 0 | AW66: 41334 | BN66: Terminated | BO66: Terminated | BY66: No | CK66: NF
A67: 71 | B67: C4/001 | C67: Ayodele | D67: John | E67: Alonge | F67: Man | G67: 4 | H67: Nigeria | I67: University of Ibadan | J67: Communication and Information | K67: School of Journalism and Mass Communication | L67: University of Nairobi | M67: No | N67: K90/97550/2015 | O67: Married | P67: Married | R67: aalonge@cartafrica.org | S67: ayoalonge@gmail.com | T67: +2348023594427 | U67: Master of Publishing and Copyright Studies | V67: 27906 | W67: Efficacy of Social Media and Mobile Technology Use for HIV/AIDS Knowledge and Prevention among Teenagers in South-West Nigeria | X67: Field | Y67: No | Z67: Primary | AA67: 33 | AB67: 42277 | AC67: 41699 | AE67: Prof wanbii Kiai | AF67: Dr Ndei Ndati | AH67: =COUNTA(AE67:AG67) -> 2 | AI67: Host | AL67: Yes | AO67: Academic | AP67: Librarian II | AQ67: Lecturer II | AR67: Yes | AT67: UNIVERSITY OF IBADAN | AU67: 0000-0001-6014-3271 | AW67: 41700 | AX67: 41946 | AY67: Yes | BE67: The use of social media for HIV and AIDS communication among university undergraduatres in South - West Nigeria | BF67: 42585 | BG67: Yes | BH67: 42793 | BI67: Yes | BJ67: 42951 | BM67: 43089 | BN67: Completed | BO67: =DATEDIF(AW67,BM67, "M")+1 -> 46 | BP67: =DATEDIF(AX67,BM67, "M")+1 -> 38 | BR67: 2 | BS67: 0 | BT67: 2 | BU67: 3 | BV67: 1 | BW67: 0 | BX67: 1 | BY67: No | BZ67: 0 | CE67: No | CH67: 2 | CI67: 3 | CJ67: 2 | CK67: FF
A68: 72 | B68: C4/002 | C68: Admire | D68: Takuranhamo | E68: Chikandiwa | F68: Man | G68: 4 | H68: South Africa | I68: University of the Witwatersrand | J68: EPIDEMIOLOGY | K68: WITS Reproductive and HIV Research Institute | L68: University of the Witwatersrand | M68: Yes | N68: 769258 | O68: Married | P68: Married | Q68: Married | R68: achikandiwa@cartafrica.org | S68: achikandiwa@gmail.com | T68: 27717388187 | U68: Master of Public Health | V68: 29840 | W68: The effects of HIV infection and treatment on the epidemiology of sexually transmitted infections in men in South Africa | X68: Clinical research | Y68: yes | Z68: Primary | AA68: 6 | AB68: 42809 | AC68: 41699 | AE68: Sinead Delany - Moretlwe | AH68: =COUNTA(AE68:AG68) -> 1 | AI68: Home | AL68: Yes | AO68: Researcher | AP68: Researcher | AQ68: Epidemiologist | AR68: Yes | AT68: UNIVERSITY OF THE WITWATERSRAND | AU68: 0000-0003-4954-2225 | AW68: 41700 | AX68: 41946 | AY68: Yes | AZ68: 42341 | BA68: 42579 | BE68: Epidemiology of HPV infection and related diseases among HIV positive men in South Africa | BF68: 42950 | BG68: No | BH68: 43164 | BI68: No | BM68: 43799 | BN68: Completed | BO68: =DATEDIF(AW68,BM68, "M")+1 -> 69 | BP68: =DATEDIF(AX68,BM68, "M")+1 -> 61 | BR68: 1 | BS68: 17 | BT68: 11 | BU68: 4 | BV68: 0 | BW68: 0 | BX68: 0 | BY68: No | BZ68: 0 | CE68: No | CH68: 1 | CI68: NF | CK68: SIDA
A69: 73 | B69: C4/003 | C69: Andrew | D69: - | E69: Tamale | F69: Man | G69: 4 | H69: Uganda | I69: Makerere University | J69: Public Health | K69: Wild life and Aquatic Animal Resources | L69: Makerere University | M69: Yes | N69: 2011/HD17/18372U | O69: Married | P69: Married | Q69: Married | R69: atamale@cartafrica.org | S69: andietam@gmail.com | T69: +256752330207/256788671192 | U69: Master of Public Health | V69: 28400 | W69: Risk Assessment of mercury and lead along the fish value chain in the lake Victoria Basin | X69: Experimental model | Y69: yes | Z69: Primary | AA69: 25.5 | AB69: 41710 | AC69: 41699 | AE69: Assoc. Prof. Francis Ejobi | AF69: Prof MUYANJA Charles | AG69: Dr. Naigaga Irene | AH69: =COUNTA(AE69:AG69) -> 3 | AI69: Home | AL69: No | AO69: Academic | AP69: Assistant Lecturer | AQ69: Lecturer | AR69: No | AT69: MAKERERE UNIVERISTY | AU69: 0000-0002-9742-1172 | AW69: 41700 | AX69: 41946 | AY69: Yes | BF69: 42585 | BG69: Yes | BH69: 42793 | BI69: Yes | BM69: 42824 | BN69: Completed | BO69: =DATEDIF(AW69,BM69, "M")+1 -> 37 | BP69: =DATEDIF(AX69,BM69, "M")+1 -> 29 | BR69: 1 | BS69: 4 | BT69: 8 | BU69: 1 | BV69: 0 | BW69: 0 | BX69: 0 | BY69: No | BZ69: 0 | CE69: No | CH69: 3 | CI69: 4 | CK69: SIDA
A70: 74 | B70: C4/004 | C70: Boladale | D70: Moyosore | E70: Mapayi | F70: Woman | G70: 4 | H70: Nigeria | I70: Obafemi Awolowo University | J70: Psychology | K70: Mental Health | L70: Obafemi Awolowo University | M70: Yes | N70: CLI/12/13/H/2219 | O70: Married | P70: Married | Q70: Married | R70: bmapayi@cartafrica.org | S70: daledosu@yahoo.com | T70: +2348033930096 | U70: Msc Clinical Psychology | V70: 27152 | W70: Integration of FP Services into Mental Health services: An Assessment of Psychosocial Correlates of uptake and continuance of mentally ill females at the Psychiatric Clinic of OAU Teaching Clinical research | X70: Clinical research | Y70: No | Z70: Primary | AA70: 14 | AB70: 41348 | AC70: 41699 | AE70: Ukpong Morenike | AF70: Harrison Abigail | AH70: =COUNTA(AE70:AG70) -> 2 | AI70: Home | AL70: Yes | AO70: Academic | AP70: Lecturer | AQ70: Associate Professor | AR70: Yes | AS70: Vice Dean, Faculty of clinical Sciences | AT70: OBAFEMI AWOLOWO UNIVERSITY | AU70: 0000-0002-0596-2132 | AW70: 41700 | AX70: 41946 | AY70: Yes | BE70: Integratining family planning into mental helath services for women attending the psychiatric outpatient clinic of Obafemi Awolowo University Teaching Clinical researchs Complex, Ile-Ife | BF70: 42585 | BG70: Yes | BH70: 42793 | BI70: Yes | BM70: 42825 | BN70: Completed | BO70: =DATEDIF(AW70,BM70, "M")+1 -> 37 | BP70: =DATEDIF(AX70,BM70, "M")+1 -> 29 | BQ70: Integratining family planning into mental helath services for women attending the psychiatric outpatient clinic of Obafemi Awolowo University Teaching Clinical researchs Complex, Ile-Ife | BR70: 9 | BS70: 6 | BT70: 15 | BU70: 0 | BV70: 1 | BW70: 0 | BX70: 0 | BY70: No | BZ70: 0 | CE70: No | CH70: 3 | CI70: 3 | CK70: SIDA
A71: 75 | B71: C4/005 | C71: Bolutife | D71: Ayokunnu | E71: Olusanya | F71: Man | G71: 4 | H71: Nigeria | I71: University of Ibadan | J71: Medicine | K71: Epidemiology and Medical Statistics | L71: University of Ibadan | M71: Yes | N71: 65466 | O71: Married | P71: Married | Q71: Married | R71: bolusanya@cartafrica.org | S71: bolutifeo@yahoo.com | T71: +2348034051563 | U71: M.Sc Epidemiology & Medical Statistics | V71: 27687 | W71: Assessment of the magnitude, causes and risk factors of childhood blindness in Oyo state, Nigeria | X71: Field | Y71: No | Z71: Primary | AA71: 3 | AB71: 41830 | AC71: 41699 | AE71: Prof. Ajayi Ikeoluwapo | AF71: Prof Baiyeroju Aderonke | AH71: =COUNTA(AE71:AG71) -> 2 | AI71: Home | AL71: Yes | AO71: Academic | AP71: Lecturer | AQ71: Associate professor | AR71: Yes | AT71: UNIVERSITY OF IBADAN | AU71: 0000-0002-8027-2844 | AW71: 41700 | AX71: 41946 | AY71: Yes | AZ71: 42866 | BA71: 42829 | BB71: 42863 | BE71: Development and validation of a screening tool for the early detection of blinding eye diseases among infants attending immunization centres in Ibadan, Nigeria | BF71: 42950 | BG71: No | BH71: 43164 | BI71: No | BM71: 44260 | BN71: Completed | BO71: =DATEDIF(AW71,BM71, "M")+1 -> 85 | BP71: =DATEDIF(AX71,BM71, "M")+1 -> 77 | BR71: 14 | BS71: 17 | BT71: 2 | BU71: 5 | BV71: 5 | BW71: 0 | BX71: 0 | BY71: No | BZ71: 0 | CE71: No | CH71: 2 | CI71: 2 | CK71: WT
A72: 76 | B72: C4/006 | C72: Chrispus | D72: - | E72: Mayora | F72: Man | G72: 4 | H72: Uganda | I72: Makerere University | J72: Public health | K72: School of public health | L72: University of the Witwatersrand | M72: No | N72: 1018550 | O72: Married | P72: Married | Q72: Married | R72: cmayora@cartafrica.org | S72: cmayora@musph.ac.ug | T72: +256773313016 | U72: Master of Health Economics | V72: 29807 | W72: Scaling up Community Health workers (CHWs) program in Uganda: Implications for Human Resources for Health Management (HRHM) | X72: Field | Y72: No | Z72: Primary | AA72: 13.5 | AB72: 42005 | AC72: 41699 | AE72: Prof. Ngianga Kandala Bakwin | AF72: Dr. Henry Wamani | AG72: Dr. Elizabeth Ekirapa-Kiracho | AH72: =COUNTA(AE72:AG72) -> 3 | AI72: Host | AL72: Yes | AO72: Academic | AP72: Assistant Lecturer | AQ72: Assistant Lecturer | AR72: No | AT72: MAKERERE UNIVERSITY | AU72: 0000-0002-6640-6519 | AW72: 41700 | AX72: 41946 | AY72: Yes | AZ72: 42104 | BA72: 42109 | BF72: 42585 | BG72: Yes | BH72: 42793 | BI72: Yes | BM72: 44365 | BN72: Completed | BO72: =DATEDIF(AW72,BM72, "M")+1 -> 88 | BP72: =DATEDIF(AX72,BM72, "M")+1 -> 80 | BQ72: Retail drug shops market in Uganda: Incentives, effect on health care system, and implications care system, and implications for child health | BR72: 1 | BS72: 11 | BT72: 3 | BU72: 2 | BV72: 0 | BW72: 0 | BX72: 0 | BY72: No | BZ72: 0 | CE72: No | CH72: 1 | CI72: 2 | CK72: SIDA
A73: 77 | B73: C4/007 | C73: Caroline | D73: Jepkoech | E73: Sawe | F73: Woman | G73: 4 | H73: Kenya | I73: Moi University | J73: Applied Human Nutrition | K73: Department of Food Science, Nutrition and Technology | L73: University of Nairobi | M73: No | N73: A80/96627/2014 | O73: Married | P73: Married | R73: csawe@cartafrica.org | S73: carolsawej@yahoo.com | T73: +254721540248 | U73: Master of Public Health | V73: 29345 | W73: Assess the Impact of Community strategy program in Nutritional Status of children under five years in Uasin Gishu County | X73: Field | Y73: No | Z73: Primary | AA73: 17 | AB73: 41730 | AC73: 41699 | AE73: Prof W Kogi-Makau | AF73: Prof Grace A. Ettyang | AG73: Dr Charkes O Kimamo | AH73: =COUNTA(AF73:AG73) -> 2 | AI73: Host | AL73: Yes | AO73: Academic | AP73: Administrator | AQ73: Lecturer | AR73: Yes | AT73: MOI UNIVERSITY | AU73: 0000-0002-9808-4091 | AW73: 41700 | AX73: 41946 | AY73: Yes | AZ73: 42047 | BA73: 42073 | BE73: Impact of community health workers on nutritional status and cognitive development of children aged less than two years in Kisumu County, Kenya | BF73: 42585 | BG73: Yes | BH73: 42793 | BI73: Yes | BM73: 44442 | BN73: Completed | BO73: =DATEDIF(AW73,BM73, "M")+1 -> 91 | BP73: =DATEDIF(AX73,BM73, "M")+1 -> 83 | BR73: 0 | BS73: 0 | BT73: 0 | BU73: 0 | BV73: 0 | BW73: 0 | BX73: 0 | BY73: JAS 3, 2016 | BZ73: 0 | CE73: No | CH73: 1 | CI73: 2 | CK73: SIDA
A74: 78 | B74: C4/008 | C74: Dieter | E74: Hartmann | F74: Man | G74: 4 | H74: South Africa | I74: University of the Witwatersrand | J74: Civil Engineering | K74: School of Mechanical, Industrial and Aeronautical Engineering | L74: University of the Witwatersrand | M74: Yes | O74: Married | P74: Married | Q74: Married | R74: dhartmann@cartafrica.org | S74: Dieter.Hartmann@wits.ac.za | T74: 27716861252 | U74: M.Sc Industrial Enginnering | V74: 29781 | W74: Determining a framework of benchmarks for efficient healthcare delivery in South Africa. | X74: Clinical research | Y74: No | Z74: Primary | AA74: 12 | AB74: 41617 | AC74: 41699 | AE74: Prof. Alex van den Heever | AH74: =COUNTA(AE74:AG74) -> 1 | AI74: Home | AL74: No | AO74: Academic | AP74: Lecturer | AT74: UNIVERSITY OF THE WITWATERSRAND | AU74: 0000-0001-9641-0095 | AW74: 41700 | AX74: 41946 | AY74: Yes | AZ74: 42846 | BA74: 42509 | BE74: Demand management in South African Public Healthcare: The case for failure demand | BF74: 43315 | BG74: No | BH74: 43528 | BI74: No | BM74: 44658 | BN74: Completed | BO74: =DATEDIF(AW74,BM74, "M")+1 -> 98 | BP74: =DATEDIF(AX74,BM74, "M")+1 -> 90 | BQ74: Demand management in healthcare service delivery: The case for failure demand | BR74: 4 | BS74: 5 | BT74: 0 | BU74: 2 | BV74: 3 | BW74: 0 | BX74: 0 | BY74: No | BZ74: 0 | CE74: No | CH74: 0 | CI74: 1 | CK74: SIDA
A75: 79 | B75: C4/009 | C75: Winnie | D75: Chepkurui | E75: Mutai | F75: Woman | G75: 4 | H75: Kenya | I75: University of Nairobi | J75: Medical Bacteriology | K75: Medical Microbiology | L75: University of Nairobi | M75: Yes | N75: H80/99967/2015 | O75: Married | P75: Separated | Q75: Separated | R75: wmutai@cartafrica.org | S75: vynnmutai@gmail.com; vynnemutai@yahoo.com | T75: +254724886584 | U75: Master in medical microbiology | V75: 29842 | W75: Molecular epidemiology of Clostridium difficile among patients in Kenyatta National Clinical research | X75: Clinical research | Y75: yes | Z75: Primary | AA75: 37 | AB75: 42078 | AC75: 41699 | AE75: Prof. Omu Anzala | AH75: =COUNTA(AE75:AG75) -> 1 | AI75: Home | AL75: Yes | AO75: Academic | AP75: Tutorial Fellow | AQ75: Tutorial Fellow | AT75: UNIVERSITY OF NAIROBI | AU75: 0000-0003-0612-9430 | AW75: 41700 | AX75: 41946 | AY75: Yes | AZ75: 43699 | BA75: 42238 | BF75: 42585 | BG75: Yes | BH75: 42793 | BI75: Yes | BM75: 45191 | BN75: Completed | BO75: =DATEDIF(AW75,BM75, "M")+1 -> 115 | BP75: =DATEDIF(AX75,BM75, "M")+1 -> 107 | BQ75: Molecular Epidemiology of Clostridiodes Difficile Among Inpatients Presenting with Diarrhea in Selected Clinical researchs in Nairobi, Kenya.’ | BR75: 0 | BS75: 5 | BT75: 0 | BU75: 1 | BV75: 0 | BW75: 0 | BX75: 0 | BY75: JAS 3, 2016 | BZ75: 0 | CE75: No | CH75: 1 | CI75: 3 | CK75: SIDA
A76: 80 | B76: C4/010 | C76: Tumaini | D76: Chiseko | E76: Malenga | F76: Woman | G76: 4 | H76: Malawi | I76: University of Malawi and Associates | J76: Medical Athropology | K76: Health Systems and Policy Development | L76: University of Malawi and Associates | M76: Yes | N76: 201380012572 | O76: Single | P76: Married | Q76: Married | R76: tmalenga@cartafrica.org | S76: tmalenga@gmail.com | T76: +265999544544 | U76: M.Sc International Development | V76: 30933 | W76: Determining the predominant motivations that promote transactional sex in densely populated areas in Malawi. | X76: Field | Y76: No | Z76: Primary | AA76: 36 | AB76: 41729 | AC76: 41699 | AE76: Prof Umar Eric | AF76: Prof Griffiths Frances | AG76: Prof Van den Berg Marrit | AH76: =COUNTA(AE76:AG76) -> 3 | AI76: Home | AL76: Yes | AO76: Researcher | AP76: Research Administrator | AQ76: Research and Policy Analyst | AR76: Yes | AT76: African Institute For Development Policy (AFIDEP) | AU76: 0000-0002-7269-0405 | AW76: 41700 | AX76: 41946 | AY76: Yes | BF76: 42585 | BG76: Yes | BH76: 42793 | BI76: Yes | BK76: 44176 | BM76: 44539 | BN76: Completed | BO76: =DATEDIF(AW76,BM76, "M")+1 -> 94 | BP76: =DATEDIF(AX76,BM76, "M")+1 -> 86 | BR76: 0 | BS76: 6 | BT76: 0 | BU76: 1 | BV76: 0 | BW76: 0 | BX76: 0 | BY76: No | BZ76: 0 | CE76: No | CH76: 0 | CI76: 1 | CK76: FF
A77: 81 | B77: C4/011 | C77: Flavia | D77: Kiweewa | E77: Matovu | F77: Woman | G77: 4 | H77: Uganda | I77: Makerere University | J77: PUBLIC HEALTH | K77: PUBLIC HEALTH | L77: University of the Witwatersrand | M77: No | N77: 1060654 | O77: Married | P77: Married | Q77: Married | R77: fmatovu@cartafrica.org | S77: fmatovu@mujhu.org | T77: +256772544759/256702544759 | U77: M.Sc Epidemiology | V77: 28080 | W77: Bone Mineral Density Study in Young Adult Women on Depot-medroxyprogesterone at the Mulago FP Clinic, Uganda | X77: Clinical research | Y77: yes | Z77: Primary | AA77: 15.5 | AB77: 42886 | AC77: 41699 | AE77: Dr. Mags Beksinska | AH77: =COUNTA(AE77:AG77) -> 1 | AI77: Host | AL77: Yes | AO77: Researcher | AP77: Researcher | AQ77: Director of Research | AR77: Yes | AT77: MAKERERE UNIVERSITY | AU77: 0000-0002-0046-4353 | AW77: 41700 | AX77: 41946 | AY77: Yes | AZ77: 42207 | BA77: 43503 | BE77: Bone mineral density in a cohort of young women using Tenofovir and Depo-Provera | BF77: 42585 | BG77: Yes | BH77: 42793 | BI77: Yes | BM77: 44508 | BN77: Completed | BO77: =DATEDIF(AW77,BM77, "M")+1 -> 93 | BP77: =DATEDIF(AX77,BM77, "M")+1 -> 85 | BR77: 1 | BS77: 15 | BT77: 6 | BU77: 1 | BV77: 1 | BW77: 0 | BX77: 0 | BY77: No | BZ77: 0 | CE77: No | CH77: NF | CI77: NF | CK77: WT
A78: 82 | B78: C4/012 | C78: Grace | D78: Wambura | E78: Mbuthia | F78: Woman | G78: 4 | H78: Kenya | I78: Moi University | J78: Anthropology | K78: Medical anthropology | L78: University of Nairobi | M78: No | N78: N79/94988/14 | O78: Married | P78: Married | Q78: Married | R78: gmbuthia@cartafrica.org | S78: gmbuthia2002@yahoo.co.uk | T78: +254 722 287 196 | U78: MPH-Epidemiology and disease control | V78: 29172 | W78: Assessment of the impact of community health workers programme in the control of tuberculosis in remote pastoralists communities -Kenya | X78: Field | Y78: No | Z78: Primary | AA78: 10 | AB78: 41913 | AC78: 41699 | AE78: Prof. Charles Owour Olungah | AF78: Dr. Tom Ondicho | AH78: =COUNTA(AE78:AG78) -> 2 | AI78: Host | AL78: Yes | AO78: Academic | AP78: Assistant Lecturer | AQ78: Lecturer | AR78: Yes | AT78: JKUAT | AU78: 0000-0003-0994-5249 | AW78: 41701 | AX78: 41946 | AY78: Yes | BE78: Perceptions, stigma and treatment pathways among Tuberclosis patients in West Pokot County, Kenya | BF78: 42585 | BG78: Yes | BH78: 42793 | BI78: Yes | BM78: 43242 | BN78: Completed | BO78: =DATEDIF(AW78,BM78, "M")+1 -> 51 | BP78: =DATEDIF(AX78,BM78, "M")+1 -> 43 | BQ78: Treatment pathways perceptions and stigma among tuberculosis patients in West- Pokot County Kenya | BR78: 2 | BS78: 3 | BT78: 5 | BU78: 6 | BV78: 1 | BW78: 0 | BX78: 0 | BY78: No | BZ78: 0 | CE78: No | CH78: 2 | CI78: 3 | CK78: WT
A79: 83 | B79: C4/013 | C79: Henry | E79: Zakumumpa | F79: Man | G79: 4 | H79: Uganda | I79: Makerere University | J79: Public Health | K79: Health Policy, Planning and Management | L79: Makerere University | M79: Yes | O79: Married | P79: Married | Q79: Married | R79: hzakumpa@cartafrica.org | S79: zakumumpa@yahoo.com | T79: +256772 520519 | U79: Master of Arts (Social Sector Planning) | V79: 27712 | W79: Characterizing the sustainability of donor-funded ART programs in Uganda: | X79: Field | Y79: No | Z79: Primary | AA79: 9.5 | AB79: 41604 | AC79: 41699 | AE79: Prof. Freddie Ssemgooba | AF79: Prof Sara Bennett | AH79: =COUNTA(AE79:AG79) -> 2 | AI79: Home | AL79: Yes | AO79: Academic | AP79: Assistant Registrar | AQ79: Post Doc Research Fellow | AR79: Yes | AT79: MAKERERE UNIVERISTY | AU79: 0000-0002-8169-1151 | AW79: 41702 | AX79: 41946 | AY79: Yes | BE79: Examining the sustainability of anti - retroviral therapy (ART) scale - up implementation in health facilities in Uganda | BF79: 42585 | BG79: Yes | BH79: 43164 | BI79: No | BJ79: 43256 | BK79: 43378 | BL79: 43399 | BM79: 43399 | BN79: Completed | BO79: =DATEDIF(AW79,BM79, "M")+1 -> 56 | BP79: =DATEDIF(AX79,BM79, "M")+1 -> 48 | BQ79: Examining the sustainability of anti - retroviral therapy (ART) scale - up implementation in health facilities in Uganda | BR79: 0 | BS79: 6 | BT79: 19 | BU79: 3 | BV79: 0 | BW79: 0 | BX79: 0 | BY79: No | BZ79: 0 | CE79: No | CH79: 2 | CI79: 3 | CK79: SIDA
A80: 84 | B80: C4/014 | C80: Irene | D80: Richard | E80: Moshi | F80: Woman | G80: 4 | H80: Tanzania | I80: Ifakara Health Institute | J80: Social Sciences/Medical Athropology | K80: Centre for Health Policy | L80: University of the Witwatersrand | M80: No | N80: 1197596 | P80: Married | Q80: Married | R80: imoshi@cartafrica.org | S80: imoshi@ihi.or.tz | T80: +255 712498879 | U80: MA Demography | V80: 30809 | W80: Exploring relationships between outdoor human activities and persistent malaria transmission in rural Tanzanian populations | X80: Field | Y80: No | Z80: Primary | AA80: 9.5 | AB80: 42036 | AC80: 41699 | AE80: Distinguished Proffesor, Lenore Manderson | AF80: Associated Prof. Ladislaus Mnyone | AG80: Distinguished Professor. Moureen Coetzee | AH80: =COUNTA(AE80:AG80) -> 3 | AI80: Home | AL80: Yes | AO80: Researcher | AP80: Research Officer | AQ80: Research Scientist | AR80: Yes | AT80: IFAKARA HEALTH INSTITUTE | AU80: 0000-0002-9516-6657 | AW80: 41703 | AX80: 41946 | AY80: Yes | AZ80: 42205 | BA80: 42230 | BE80: Outdoor Malaria Transmission: Human activities and the risks of acquiring malaria infection in rural communities of Morogoro Region, Tanzania | BF80: 42585 | BG80: Yes | BH80: 42793 | BI80: Yes | BM80: 43830 | BN80: Completed | BO80: =DATEDIF(AW80,BM80, "M")+1 -> 70 | BP80: =DATEDIF(AX80,BM80, "M")+1 -> 62 | BR80: 1 | BS80: 5 | BT80: 3 | BU80: 2 | BV80: 0 | BW80: 0 | BX80: 0 | BY80: JAS 3, 2016 | BZ80: 0 | CE80: No | CH80: 1 | CI80: 2 | CK80: SIDA
A81: 85 | B81: C4/015 | C81: Magutah | D81: Joel | E81: Karani | F81: Man | G81: 4 | H81: Kenya | I81: Moi University | J81: Medical physiology | K81: Medical physiology | L81: University of Nairobi | M81: No | N81: H80/95068/2014 | O81: Married | P81: Married | Q81: Married | R81: jkarani@cartafrica.org | S81: kmagutah@gmail.com | T81: +254721545063 | U81: Master of Science. Medical Physiology | V81: 28497 | W81: Cardio-respiratory fitness trends in physically healthy Kenyan Populace from rural and Urban set-ups | X81: Field | Y81: yes | Z81: Primary | AA81: 13 | AB81: 41642 | AC81: 41699 | AE81: Prof. Nilesh B. Patel | AF81: Prof. Kihumbu Thairu | AH81: =COUNTA(AE81:AG81) -> 2 | AI81: Host | AL81: Yes | AO81: Academic | AP81: Graduate Assistant | AQ81: Lecturer | AR81: Yes | AT81: MOI UNIVERSITY | AU81: 0000-0003-3105-2981 | AW81: 41704 | AX81: 41946 | AY81: Yes | AZ81: 42125 | BA81: 42156 | BB81: 42217 | BE81: The effect of short and long bouts of Home based moderate intensity exercises on cardiorespiratory fitness among sedentary Western Kenya Adults Aged at least 50 Years. | BF81: 42585 | BG81: Yes | BH81: 42791 | BI81: Yes | BJ81: 43115 | BK81: 43349 | BL81: 43426 | BM81: 43434 | BN81: Completed | BO81: =DATEDIF(AW81,BM81, "M")+1 -> 57 | BP81: =DATEDIF(AX81,BM81, "M")+1 -> 49 | BQ81: The Effect of Short and Long Bouts of Home-based Moderate Intensity Exercises on Cardiorespiratory Fitness among Sedentary Western-Kenya Adults Aged at least 50 Years. | BR81: 1 | BS81: 4 | BT81: 3 | BU81: 2 | BV81: 0 | BW81: 0 | BX81: 0 | BY81: No | BZ81: 0 | CE81: No | CH81: 2 | CI81: 2 | CK81: SIDA
A82: 86 | B82: C4/016 | C82: Jackline | D82: Chepchirchir | E82: Sitienei | F82: Woman | G82: 4 | H82: Kenya | I82: Moi University | J82: Public Health | K82: Center of Health Policy | L82: University of the Witwatersrand | M82: No | N82: 1061559 | P82: Married | R82: jsitienei@cartafrica.org | S82: sitieneij@yahoo.com | T82: +254722926800 | U82: Master of International Research Ethics | V82: 25297 | W82: Multilevel Community Participation in Health Facilities, Western Kenya | X82: Field | Y82: No | Z82: Primary | AA82: 16 | AB82: 41693 | AC82: 41699 | AE82: Mabel Nangami | AH82: =COUNTA(AE82:AG82) -> 1 | AI82: Home | AL82: No | AO82: Academic | AP82: Assistant Lecturer | AQ82: Lecturer | AR82: Yes | AT82: MOI UNIVERSITY | AU82: 0000-0001-6182-2209 | AW82: 41700 | AX82: 41946 | AY82: Yes | AZ82: 42555 | BA82: 42989 | BF82: 42585 | BG82: Yes | BH82: 42793 | BI82: Yes | BN82: In progress | BR82: 2 | BS82: 3 | BT82: 0 | BU82: 3 | BV82: 0 | BW82: 0 | BX82: 0 | BY82: No | BZ82: 0 | CE82: No | CH82: NF | CI82: NF | CK82: CARNEGIE
A83: 87 | B83: C4/017 | C83: Kaitesi | D83: Batamuliza | E83: Mukara | F83: Woman | G83: 4 | H83: Rwanda | I83: University of Rwanda | J83: Public Health | K83: Health Policy | L83: Makerere University | M83: No | N83: 2014/HD07/18709X | O83: Separated | P83: Divorced | Q83: Divorced | R83: kmukara@cartafrica.org | S83: kaibat@hotmail.com | T83: +250 788467587 | U83: M.Sc Audiology | V83: 28294 | W83: Audiology: Planning and policies for improved care in resource limited settings – the case of Rwanda | X83: Field | Y83: No | Z83: Primary | AA83: 7.5 | AB83: 42353 | AC83: 41699 | AE83: Dr. Peter Waiswa | AH83: =COUNTA(AE83:AG83) -> 1 | AI83: Host | AL83: Yes | AO83: Academic | AP83: Lecturer | AQ83: CEO | AR83: Yes | AT83: HEARING HEALTH RWANDA (2019) | AU83: 0000-0003-0585-2846 | AW83: 41700 | AX83: 41946 | AY83: Yes | BF83: 42585 | BG83: Yes | BH83: 42793 | BI83: Yes | BK83: 44221 | BM83: 44333 | BN83: Completed | BO83: =DATEDIF(AW83,BM83, "M")+1 -> 87 | BP83: =DATEDIF(AX83,BM83, "M")+1 -> 79 | BQ83: Prevalence of ear infections and care seeking practices in children under five in a dsitrict of Kigali city, Rwanda | BR83: 0 | BS83: 4 | BT83: 0 | BU83: 0 | BV83: 1 | BW83: 0 | BX83: 0 | BY83: No | BZ83: 0 | CE83: No | CH83: 2 | CI83: 2 | CK83: SIDA/DAAD
A84: 88 | B84: C4/018 | C84: Harrison | D84: Lackson | E84: Tembo | F84: Man | G84: 4 | H84: Malawi | I84: University of Malawi and Associates | J84: Public Health | K84: Basic Medical Sciences | L84: University of Malawi and Associates | M84: Yes | N84: 2013-07-00251 | O84: NF | P84: Married | R84: ltembo@cartafrica.org | S84: ltembo@medcol.mw | T84: +265997723601 | U84: M.Sc Human Anatomy | V84: 30152 | W84: Assessing the effect of HIV/AIDS on bone microstructure and composition on bone tissue. | X84: Clinical research | Y84: yes | Z84: Primary | AA84: 25 | AB84: 41692 | AC84: 41699 | AD84: 43867 | AE84: Professor Amadi O. Ihunwo | AH84: =COUNTA(AE84:AG84) -> 1 | AI84: Other | AL84: Yes | AO84: Academic | AP84: Lecturer | AT84: UNIVERSITY OF MALAWI | AW84: 41700 | AX84: 41946 | AY84: Yes | BF84: 42585 | BG84: Yes | BI84: No | BN84: Terminated | BO84: Terminated | BR84: 0 | BS84: 2 | BT84: 0 | BU84: 1 | BV84: 0 | BW84: 0 | BX84: 0 | BY84: No | BZ84: 0 | CE84: No | CH84: NF | CI84: NF | CK84: SIDA
A85: 89 | B85: C4/019 | C85: Mohamed | D85: Kassim | E85: Ally | F85: Man | G85: 4 | H85: Tanzania | I85: University of Dar es Salaam | J85: Library Science | K85: Information Studies | L85: University of Dar es Salaam | M85: Yes | N85: 1034515 | O85: Married | P85: Married | Q85: Married | R85: mkassim@cartafrica.org | S85: mohdie2@yahoo.com | T85: +255 713 742 525 | U85: M.A Information Studies | V85: 29764 | W85: Maternal Health Information Needs and Information Seeking Behavior of Women of Reproductive Age in Rural Tanzania | X85: Field | Y85: No | Z85: Primary | AA85: 28 | AB85: 41730 | AC85: 41699 | AE85: Prof. Jangawe Msuya | AH85: =COUNTA(AE85:AG85) -> 1 | AI85: Home | AL85: No | AO85: Researcher | AP85: Assistant Lecturer | AQ85: Associate Professor | AR85: Yes | AT85: UNIVERSITY OF DAR ES SALAAM | AU85: 0000-0002-3016-9283 | AW85: 41700 | AX85: 41946 | AY85: Yes | BF85: 42585 | BG85: Yes | BH85: 42793 | BI85: Yes | BM85: 43201 | BN85: Completed | BO85: =DATEDIF(AW85,BM85, "M")+1 -> 50 | BP85: =DATEDIF(AX85,BM85, "M")+1 -> 42 | BQ85: Maternal health information needs and seeking behaviour of women of reproductive age in rural Tanzania: a case of Mpwapwa district, Dodoma region | BR85: 0 | BS85: 0 | BT85: 6 | BU85: 1 | BV85: 0 | BW85: 0 | BX85: 0 | BY85: No | BZ85: 0 | CE85: No | CH85: 1 | CI85: 1 | CK85: SIDA
A86: 90 | B86: C4/020 | C86: Mbithi | D86: Michael | E86: Mutua | F86: Man | G86: 4 | H86: Kenya | I86: APHRC | J86: Public Health | K86: Research | L86: University of the Witwatersrand | M86: No | N86: SSP11/12/H/2901 | O86: Married | P86: Married | Q86: Married | R86: mmutua@cartafrica.org | S86: mutua_mike@yahoo.com;mmutua@bristolpark.or.ke; mutuamike@gmail.com | T86: +25422365431 | U86: Master of Social Statistics | V86: 28270 | W86: Abortion and Post Abortion Care in Kenya | X86: Field | Y86: No | Z86: Primary | AA86: 21 | AB86: 41756 | AC86: 41699 | AE86: Prof Manderson Lenore | AF86: Prof Musenge Eustasius | AG86: Dr Achia Thomas | AH86: =COUNTA(AE86:AG86) -> 3 | AI86: Host | AL86: Yes | AO86: Researcher | AP86: Statistical Data Analyst | AQ86: Consultant | AR86: Yes | AT86: SELF EMPLOYED (2019) | AU86: 0000-0002-7326-3886 | AW86: 41700 | AX86: 41946 | AY86: Yes | AZ86: 42235 | BA86: 42195 | BE86: Quality of post abortion Care in Kenya | BF86: 42585 | BG86: Yes | BH86: 42793 | BI86: Yes | BM86: 43657 | BN86: Completed | BO86: =DATEDIF(AW86,BM86, "M")+1 -> 65 | BP86: =DATEDIF(AX86,BM86, "M")+1 -> 57 | BR86: 2 | BS86: 17 | BT86: 6 | BU86: 3 | BV86: 1 | BW86: 0 | BX86: 0 | BY86: No | BZ86: 0 | CE86: No | CH86: 3 | CI86: 3 | CK86: SIDA
A87: 91 | B87: C4/021 | C87: Modupe | D87: Oladunni | E87: Taiwo | F87: Woman | G87: 4 | H87: Nigeria | I87: Obafemi Awolowo University | J87: Health Psychology | K87: Center for Gender and Social Policy Studies | L87: Obafemi Awolowo University | M87: Yes | N87: 0702658H | O87: Married | P87: Married | Q87: Married | R87: mtaiwo@cartafrica.org | S87: oladunnitaiwo@gmail.com | T87: +234(0)8062234960 | U87: MPA- Reproductive Health | V87: 26239 | W87: Relationship between Psychological well-being and HAART adherence among HIV/AIDS infected persons in three nationally designated treatment centers in Southwest Nigeria | X87: Field | Y87: No | Z87: Primary | AA87: 26 | AB87: 41156 | AC87: 41699 | AE87: Professor Funmi Togonu-Bickersteth | AH87: =COUNTA(AE87:AG87) -> 1 | AI87: Home | AL87: Yes | AO87: Academic | AP87: Junior Research Fellow | AT87: OBAFEMI AWOLOWO UNIVERSITY | AU87: 0000-0002-1377-3470 | AW87: 41700 | AX87: 41946 | AY87: Yes | BF87: 42585 | BG87: Yes | BH87: 42793 | BI87: Yes | BM87: 42460 | BN87: Completed | BO87: =DATEDIF(AW87,BM87, "M")+1 -> 25 | BP87: =DATEDIF(AX87,BM87, "M")+1 -> 17 | BR87: 3 | BS87: 0 | BT87: 2 | BU87: 0 | BV87: 0 | BW87: 0 | BX87: 0 | BY87: No | BZ87: 0 | CE87: No | CH87: 1 | CI87: 1 | CK87: SIDA
A88: 92 | B88: C4/022 | C88: Nkosiyazi | D88: - | E88: Dube | F88: Man | G88: 4 | H88: South Africa | I88: University of the Witwatersrand | J88: Social Development | K88: Social Work | L88: University of the Witwatersrand | M88: Yes | N88: U803/98508/2015 | O88: Married | P88: Married | Q88: Married | R88: ndube@cartafrica.org | S88: dubenkosipnj@gmail.com | T88: +27730933485 | U88: Master of Arts (Social Work – Social Development) | V88: 28287 | W88: Exploring the experiences and social complexity associated with non/disclosure of HIV status to children born HIV positive living at Child and Youth Care Centres in South Africa | X88: Field | Y88: No | Z88: Primary | AA88: 20.5 | AB88: 41640 | AC88: 41699 | AE88: Professor Edwell Kaseke | AF88: Professor Edmarie Pretorius | AH88: =COUNTA(AE88:AG88) -> 2 | AI88: Home | AL88: Yes | AO88: Academic | AP88: Tutor | AQ88: Senior Lecturer | AR88: Yes | AS88: Deputy Head of Department and course Cordinator (2021 Jan) | AT88: UNIVERSITY OF THE WITWATERSRAND | AU88: 0000-0002-3036-2008 | AW88: 41700 | AX88: 41946 | AY88: Yes | BE88: Informal social security and its contributions towards meeting the needs of the poor: The case of stokvels in Soweto, Johannesburg | BF88: 42585 | BG88: Yes | BH88: 43164 | BI88: No | BM88: 43285 | BN88: Completed | BO88: =DATEDIF(AW88,BM88, "M")+1 -> 53 | BP88: =DATEDIF(AX88,BM88, "M")+1 -> 45 | BQ88: Informal social security and its contributions towards meeting the needs of the poor: The case of stokvels in Soweto, Johannesburg | BR88: 1 | BS88: 5 | BT88: 6 | BU88: 2 | BV88: 2 | BW88: 0 | BX88: 0 | BY88: No | BZ88: 0 | CE88: No | CH88: 1 | CI88: 2 | CJ88: 1 | CK88: SIDA
A89: 93 | B89: C4/023 | C89: Nilian | D89: Ayuma | E89: Mukungu | F89: Woman | G89: 4 | H89: Kenya | I89: University of Nairobi | J89: Pharmacognosy | K89: Pharmacology and Pharmacognosy | L89: University of Nairobi | M89: Yes | N89: 2013-07-00246 | O89: Married | P89: Married | Q89: Married | R89: nmukungu@cartafrica.org | S89: nillyanne2004@yahoo.com | T89: +254 721291660 | U89: M.Sc Pharmacognosy | V89: 30065 | W89: Antimalarial activity of plants used for treating malaria in rural western Kenya | X89: Field | Y89: yes | Z89: Primary | AA89: 38 | AB89: 42065 | AC89: 41699 | AE89: Prof. Mwangi Julius | AH89: =COUNTA(AE89:AG89) -> 1 | AI89: Home | AL89: Yes | AO89: Academic | AP89: Graduate Assistant | AQ89: Lecturer | AR89: Yes | AT89: UNIVERSITY OF NAIROBI | AU89: 0000-0002-7510-247X | AW89: 41700 | AX89: 41946 | AY89: Yes | AZ89: 42199 | BA89: 42137 | BF89: 42585 | BG89: Yes | BH89: 42793 | BI89: Yes | BM89: 44827 | BN89: Completed | BO89: =DATEDIF(AW89,BM89, "M")+1 -> 103 | BP89: =DATEDIF(AX89,BM89, "M")+1 -> 95 | BR89: 0 | BS89: 1 | BT89: 0 | BU89: 1 | BV89: 0 | BW89: 0 | BX89: 0 | BY89: No | BZ89: 0 | CE89: No | CH89: 2 | CI89: 3 | CK89: SIDA
A90: 94 | B90: C4/024 | C90: Respicius | D90: Shombusho | E90: Damian | F90: Man | G90: 4 | H90: Tanzania | I90: University of Dar es Salaam | J90: Political Science and Public Administration | K90: Political Science and Public Administration | L90: University of Dar es Salaam | M90: Yes | N90: BMSP13/14/H/1471 | O90: Married | P90: Married | Q90: Married | R90: rdamian@cartafrica.org | S90: shumbusho35@gmail.com | T90: +255713428318/ 255738679039 | U90: M.A (Political Science and Public Administration | V90: 29335 | W90: Financial Accountability in Rural Public Health: The Case of Maternal Health in Kigoma and Rukwa Regions | X90: Field | Y90: No | Z90: Primary | AA90: 19.5 | AB90: 41746 | AC90: 41699 | AE90: Dr Benson Alfred Bana | AF90: Professor/Kessy/Thebald/Ambrose | AH90: =COUNTA(AE90:AG90) -> 2 | AI90: Home | AL90: Yes | AO90: Academic | AP90: Assistant Lecturer | AQ90: Lecturer | AR90: Yes | AT90: UNIVERSITY OF DAR ES SALAAM | AU90: 0000-0001-9761-2270 | AW90: 41700 | AX90: 41946 | AY90: Yes | AZ90: 41706 | BB90: 42080 | BE90: Community empowerment and accountability in Rural Primary Health Care: The case of Kasulu District in Tanzania | BF90: 42585 | BG90: Yes | BH90: 42793 | BI90: Yes | BJ90: 43165 | BK90: 43376 | BL90: 43399 | BM90: 43417 | BN90: Completed | BO90: =DATEDIF(AW90,BM90, "M")+1 -> 57 | BP90: =DATEDIF(AX90,BM90, "M")+1 -> 49 | BQ90: Community empowerment and accountability in Rural Primary Health Care: The case of Kasulu District in Tanzania | BR90: 0 | BS90: 0 | BT90: 3 | BU90: 2 | BV90: 0 | BW90: 0 | BX90: 0 | BY90: No | BZ90: 0 | CE90: No | CH90: 2 | CI90: 2 | CK90: WT
A91: 95 | B91: C4/025 | C91: Sunday | D91: Joseph | E91: Ayamolowo | F91: Man | G91: 4 | H91: Nigeria | I91: Obafemi Awolowo University | J91: Nursing | K91: Learners’ Support Services, Centre for Distance Learning | L91: Obafemi Awolowo University | M91: Yes | O91: Married | P91: Married | Q91: Married | R91: sayamolowo@cartafrica.org | S91: olowoyamolowo@yahoo.com | T91: +2347038761908 | U91: Master of Science (MSc) in Nursing. | V91: 28031 | W91: Burden and coping pattern of pregnant teenagers and teenage mothers in selected primary health care centres in Ekiti state, Nigeria | X91: Field | Y91: No | Z91: Primary | AA91: 31.5 | AB91: 41866 | AC91: 41699 | AE91: Prof Irinoye Oladunni Omolola | AH91: =COUNTA(AE91:AG91) -> 1 | AI91: Home | AL91: Yes | AO91: Academic | AP91: Lecturer II | AQ91: Senior Lecturer | AR91: Yes | AT91: OBAFEMI AWOLOWO UNIVERSITY | AU91: 0000-0003-3307-6485 | AW91: 41700 | AX91: 41946 | AY91: Yes | BF91: 42951 | BG91: No | BH91: 43164 | BI91: No | BM91: 43433 | BN91: Completed | BO91: =DATEDIF(AW91,BM91, "M")+1 -> 57 | BP91: =DATEDIF(AX91,BM91, "M")+1 -> 49 | BQ91: Effect of Technology-moderated Intervention on Family Childbirth Experiences, Maternal and Newborn outcomes in Home and Clinical research Deliveries in Ekiti State | BR91: 0 | BS91: 1 | BT91: 4 | BU91: 1 | BV91: 2 | BW91: 0 | BX91: 0 | BY91: No | BZ91: 0 | CE91: No | CH91: 2 | CI91: 3 | CK91: CARNEGIE
A92: 96 | B92: C4/026 | C92: Oladapo | D92: Oluwaseun | E92: Akinyemi | F92: Man | G92: 4 | H92: Nigeria | I92: University of Ibadan | J92: Public Health | K92: Health Policy and Management | L92: University of the Witwatersrand | M92: Yes | O92: Married | P92: married | Q92: Married | R92: aoladapo@cartafrica.org | S92: seunakinyemi@hotmail.com | T92: 2348035020136 | U92: M.Sc International Public Health | V92: 28157 | W92: Analysis of Maternal Health Policies in Nigeria: Challenges and Lessons | X92: Field | Y92: No | Z92: Primary | AA92: 17.5 | AB92: 41695 | AC92: 41699 | AE92: Mary Kawonga | AH92: =COUNTA(AE92:AG92) -> 1 | AI92: Other | AL92: No | AO92: Academic | AP92: Lecturer I | AQ92: Senior Lecturer | AR92: Yes | AT92: UNIVERSITY OF IBADAN | AU92: 0000-0003-4135-1459 | AW92: 41700 | AX92: 41946 | AY92: Yes | AZ92: 42580 | BA92: 42580 | BE92: Scale up of community-based injectable contraceptives in Gombe state, Nigeria | BF92: 42952 | BG92: No | BH92: 43164 | BI92: No | BM92: 44137 | BN92: Completed | BO92: =DATEDIF(AW92,BM92, "M")+1 -> 81 | BP92: =DATEDIF(AX92,BM92, "M")+1 -> 72 | BQ92: Scale up of community-based injectable contaceptives in Gombe, Nigeria | BR92: 5 | BS92: 17 | BT92: 16 | BU92: 0 | BV92: 2 | BW92: 0 | BX92: 0 | BY92: No | BZ92: 0 | CE92: No | CH92: 3 | CI92: 3 | CK92: CARNEGIE
A93: 97 | B93: C4/027 | C93: Sara | D93: Jewett | E93: Nieuwoudt | F93: Woman | G93: 4 | H93: South Africa | I93: University of the Witwatersrand | J93: Public Health | K93: Division of Social & Behaviour Change Communication | L93: University of the Witwatersrand | M93: Yes | O93: Married | P93: Married | Q93: Married | R93: snieuwoudt@cartafrica.org | S93: sara.nieuwoudt@gmail.com or sara.nieuwoudt@wits.ac.z | T93: +27834284392 | U93: MPH (Behavioral Sciences & Health Education) | V93: 28587 | W93: The role of social capital in health seeking and maternal and child health outcomes of urban migrants in Johannesburg, South Africa | X93: Field | Y93: No | Z93: Primary | AA93: 7 | AB93: 41867 | AC93: 41699 | AE93: Prof. Lenore Manderson | AH93: =COUNTA(AE93:AG93) -> 1 | AI93: Home | AL93: Yes | AO93: Academic | AP93: Lecturer | AQ93: Associate Professor | AR93: Yes | AS93: & Social and Behaviour Change Communication Coordinator | AT93: UNIVERSITY OF THE WITWATERSRAND | AU93: 0000-0002-6658-2061 | AW93: 41700 | AX93: 41946 | AY93: Yes | BF93: 42953 | BG93: No | BH93: 43164 | BI93: No | BM93: 43658 | BN93: Completed | BO93: =DATEDIF(AW93,BM93, "M")+1 -> 65 | BP93: =DATEDIF(AX93,BM93, "M")+1 -> 57 | BR93: 0 | BS93: 2 | BT93: 2 | BU93: 2 | BV93: 1 | BW93: 0 | BX93: 0 | BY93: No | BZ93: 365 | CE93: Yes | CH93: 1 | CI93: 1 | CK93: WT
A94: 98 | B94: C5/001 | C94: Cheikh Mbacké | E94: Faye | F94: Man | G94: 5 | H94: Senegal | I94: APHRC | J94: Public Health | K94: Research Division | L94: University of the Witwatersrand | M94: No | N94: 1513579 | O94: Married | P94: Married | Q94: Married | R94: cfaye@cartafrica.org | S94: cmfaye@hotmail.com | T94: +254739211509 | U94: Masters in Statistics | V94: 27949 | W94: Maternal characteristics,reproductive behaviors, breastfeeding practices and nutritional outcomes among children under five years in Nairobi’s informal settlements. | X94: Field | Y94: No | Z94: Primary | AA94: 5.5 | AB94: 42370 | AC94: 42064 | AE94: DonatienBeguy, PhD | AF94: Elizabeth Kimani, PhD | AG94: Sharon Fonn | AH94: =COUNTA(AE94:AG94) -> 3 | AI94: Home | AJ94: Home | AK94: Host | AL94: Yes | AM94: No | AN94: Yes | AO94: Researcher | AP94: Senior Research Officer | AQ94: Research Scientist | AR94: Yes | AS94: Head, APHRC West Africa Region Office | AT94: APHRC West Africa Regional Office - Senegal | AU94: 0000-0002-4028-0575 | AV94: No | AW94: 42065 | AX94: 42310 | AY94: Yes | BA94: 42492 | BE94: Factors associated with stunting and recovery from stunting among under-five children in Nairobi informal settlements | BF94: 42947 | BG94: Yes | BH94: 43528 | BI94: No | BM94: 43646 | BN94: Completed | BO94: =DATEDIF(AW94,BM94, "M")+1 -> 52 | BP94: =DATEDIF(AX94,BM94, "M")+1 -> 44 | BR94: 4 | BS94: 2 | BT94: 19 | BU94: 1 | BV94: 1 | BW94: 0 | BX94: 0 | BY94: No | BZ94: 0 | CE94: No | CH94: 3 | CI94: 3 | CK94: SIDA
A95: 99 | B95: C5/002 | C95: Celestin | E95: Ndikumana | F95: Man | G95: 5 | H95: Rwanda | I95: University of Rwanda | J95: Human Resource Management | K95: Development Studies | L95: Moi University | M95: No | N95: SHRD/PhDH/03/15 | O95: Married | P95: Married | Q95: Married | R95: cndikumana@cartafrica.org | S95: cndikumana@hotmail.com | T95: +250 788833975 | U95: M. BA International Business | V95: 29221 | W95: The interface of environmental management in the Clinical researchity industry in Rwanda: A practical approach to sustainable health. | X95: Field | Y95: No | Z95: Primary | AA95: 39 | AB95: 42993 | AC95: 42064 | AE95: Dr. Ruth J. Tubey | AF95: Dr. Alice Kurgat | AH95: =COUNTA(AE95:AG95) -> 2 | AI95: Host | AJ95: Host | AL95: Yes | AM95: No | AO95: Academic | AP95: Assistant Lecturer | AQ95: Senior Lecturer | AR95: Yes | AS95: Head of Department: Governance and Public Science and International Relations Administration; Political | AT95: UNIVERSITY OF RWANDA | AU95: 0000-0002-5726-6921 | AV95: No | AW95: 42065 | AX95: 42310 | AY95: Yes | AZ95: 42850 | BA95: 42863 | BE95: Effect of Human Resource Managenment Practices on the retention of professional health workers in the Public District Clinical researchs in Kigali, Rwanda | BF95: 42947 | BG95: Yes | BH95: 43164 | BI95: Yes | BM95: 43830 | BN95: Completed | BO95: =DATEDIF(AW95,BM95, "M")+1 -> 58 | BP95: =DATEDIF(AX95,BM95, "M")+1 -> 50 | BR95: 0 | BS95: 1 | BT95: 2 | BU95: 2 | BV95: 0 | BW95: 0 | BX95: 0 | BY95: No | BZ95: 0 | CE95: No | CH95: 1 | CI95: 3 | CK95: SIDA
A96: 100 | B96: C5/003 | C96: Esther | D96: Kikelomo | E96: Afolabi | F96: Woman | G96: 5 | H96: Nigeria | I96: Obafemi Awolowo University | J96: Nursing | K96: Nursing Science | L96: Obafemi Awolowo University | M96: Yes | N96: BMSP13/14/H/0859 | O96: Married | P96: Married | Q96: Married | R96: eafolabi@cartafrica.org | S96: eafolabi16@gmail.com | T96: +234 803 801 3115 | U96: M.Sc Nursing | V96: 29998 | W96: Correlation of cervical cancer risk factors with cervical smear and histopathological diagnosis among reproductive age women in Ile- Ife, Osun State. | X96: Clinical research | Y96: yes | Z96: Primary | AA96: 22 | AB96: 41748 | AC96: 42064 | AE96: Prof. Oluwafemi N. Mimiko | AF96: Dr. A. A. E Olaogun | AH96: =COUNTA(AE96:AG96) -> 2 | AI96: Home | AJ96: Home | AL96: No | AM96: Yes | AO96: Academic | AP96: Lecturer II | AQ96: Associate Professor | AR96: Yes | AT96: ARDEN UNIVERSITY (2023) | AU96: 0000-0002-0381-737X. | AV96: Yes | AW96: 42065 | AX96: 42310 | AY96: Yes | BF96: 42947 | BG96: Yes | BH96: 43164 | BI96: Yes | BM96: 43250 | BN96: Completed | BO96: =DATEDIF(AW96,BM96, "M")+1 -> 39 | BP96: =DATEDIF(AX96,BM96, "M")+1 -> 31 | BR96: 0 | BS96: 0 | BT96: 3 | BU96: 0 | BV96: 0 | BW96: 0 | BX96: 0 | BY96: No | BZ96: 0 | CE96: No | CH96: 3 | CI96: 3 | CK96: SIDA
A97: 101 | B97: C5/004 | C97: Yolanda | D97: Malele | E97: Kolisa | F97: Woman | G97: 5 | H97: South Africa | I97: University of the Witwatersrand | J97: Community Dentistry | K97: Community Dentistry | L97: University of the Witwatersrand | M97: Yes | N97: 8803014E | O97: Married | P97: Married | R97: ykolisa@cartafrica.org | S97: yolanda.kolisa@wits.ac.za | T97: 837800907 | U97: MPH, M.Dental | V97: 26236 | W97: Measurement of oral health related quality of life(OHRQoL) in HIV-infected and non-infected children: Investigation of socio- cultural influences in a South African context. | X97: Field | Y97: No | Z97: Primary | AA97: 11.5 | AB97: 42430 | AC97: 42064 | AE97: Dr. Jude Igumbor | AF97: Prof. Magnus Hakeburg | AH97: =COUNTA(AE97:AG97) -> 2 | AI97: Home | AJ97: Other | AL97: Yes | AM97: No | AO97: Academic | AQ97: Lecturer | AT97: UNIVERSITY OF THE WITWATERSRAND | AU97: 0000-0003-3368-9193 | AV97: No | AW97: 42065 | AX97: 42310 | AY97: Yes | BF97: 42947 | BG97: Yes | BH97: 43164 | BI97: Yes | BM97: 44334 | BN97: Completed | BO97: =DATEDIF(AW97,BM97, "M")+1 -> 75 | BP97: =DATEDIF(AX97,BM97, "M")+1 -> 67 | BQ97: Oral Health needs and Oral Health related Quality of Life of Adolescents Living with HIV in Johannesburg, South Africa | BR97: 2 | BS97: 5 | BT97: 1 | BU97: 1 | BV97: 0 | BW97: 0 | BX97: 0 | BY97: No | BZ97: 0 | CE97: No | CH97: 3 | CI97: 3 | CK97: SIDA
A98: 102 | B98: C5/005 | C98: Taiwo | D98: Akinyode | E98: Obembe | F98: Man | G98: 5 | H98: Nigeria | I98: University of Ibadan | J98: Public Health | K98: Health Policy | L98: University of the Witwatersrand | M98: No | N98: 951466 | O98: Married | P98: Married | R98: tobembe@cartafrica.org | S98: tobems@yahoo.com | T98: +234 805 840 9495 | U98: MPH | V98: 28992 | W98: Coping with out of pocket payment among urban poor: Findings from South Western Nigeria. | X98: Field | Y98: No | Z98: Primary | AA98: 18 | AB98: 42555 | AC98: 42064 | AE98: Dr. Oyediran Oyewole | AF98: Sharon Fonn | AH98: =COUNTA(AE98:AG98) -> 2 | AI98: Home | AJ98: Host | AL98: Yes | AM98: Yes | AO98: Academic | AT98: UNIVERSITY OF IBADAN | AU98: 0000-0001-9610-1137 | AV98: Yes | AW98: 42065 | AX98: 42310 | AY98: Yes | AZ98: 42535 | BA98: 42620 | BE98: Patterns of expenditure, coping mechanisms among urban slum dwellers admitted for emergency surgeries in Ibadan, Nigeria | BF98: 42947 | BG98: Yes | BH98: 43164 | BI98: Yes | BM98: 44529 | BN98: Completed | BO98: =DATEDIF(AW98,BM98, "M")+1 -> 81 | BP98: =DATEDIF(AX98,BM98, "M")+1 -> 73 | BQ98: Patterns of expenditure, coping mechanisms among urban slum dwellers admitted for emergency surgeries in Ibadan, Nigeria | BR98: 0 | BS98: 15 | BT98: 3 | BU98: 6 | BV98: 1 | BW98: 0 | BX98: 0 | BY98: No | BZ98: 0 | CE98: Yes | CH98: 2 | CI98: NF | CK98: SIDA
A99: 103 | B99: C5/006 | C99: Emmanuel | D99: Wilson | E99: Kaindoa | F99: Man | G99: 5 | H99: Tanzania | I99: Ifakara Health Institute | J99: Medical Entomology | K99: Environmental Health and Ecological Science | L99: University of the Witwatersrand | M99: No | N99: 1362999 | O99: Single | P99: married | Q99: Married | R99: ekaindoa@cartafrica.org | S99: ekaindoa@ihi.or.tz | T99: +255787430307 | U99: Masters of Science in Biology and Control of Parasites and Disease Vectors | V99: 31406 | W99: Assessing the impact of settlement patterns and distances between households on malaria transmission in rural Tanzanian populations. | X99: Field | Y99: yes | Z99: Primary | AA99: 8.5 | AB99: 42231 | AC99: 42064 | AE99: Fredros Okumu | AH99: =COUNTA(AE99:AG99) -> 1 | AI99: Home | AL99: Yes | AO99: Researcher | AP99: Research scientist | AQ99: Research scientist | AR99: Yes | AS99: Deputy Head, Environmental Health Dept | AT99: IFAKARA HEALTH INSTITUTE | AU99: 0000-0001-6170-5694 | AW99: 42065 | AX99: 42310 | AY99: Yes | BF99: 42947 | BG99: Yes | BH99: 43164 | BI99: Yes | BM99: 43830 | BN99: Completed | BO99: =DATEDIF(AW99,BM99, "M")+1 -> 58 | BP99: =DATEDIF(AX99,BM99, "M")+1 -> 50 | BQ99: Assessing Relationship between Human Settlement Patterns and Malaria Risk in a Residual Transmission Setting in South-Eastern Tanzania | BR99: 1 | BS99: 16 | BT99: 9 | BU99: 3 | BV99: 0 | BW99: 0 | BX99: 0 | BY99: No | BZ99: 0 | CE99: No | CH99: 0 | CI99: 1 | CK99: SIDA
A100: 104 | B100: C5/007 | C100: Esther | D100: Wamuyu | E100: Karumi | F100: Woman | G100: 5 | H100: Kenya | I100: University of Nairobi | J100: Pharmacy | K100: Pharmacology and Pharmacognosy | L100: University of Nairobi | M100: Yes | N100: U803/98509/2015 | P100: Single | R100: ekarumi@cartafrica.org | S100: e_karumi@yahoo.com | T100: +254721293354 | U100: M.Sc Pharmacognosy | V100: 29277 | W100: Antioxidant, antidiabetic and hypolipidemic activities of selected medicinal plants used by the Maasai | X100: Field | Y100: yes | Z100: Primary | AA100: 28.5 | AB100: 42255 | AC100: 42064 | AE100: Prof. Julius Wanjohi Mwangi | AF100: Dr. Kennedy Omondi Abuga | AH100: =COUNTA(AE100:AG100) -> 2 | AI100: Home | AJ100: Home | AL100: Yes | AM100: No | AO100: Academic | AP100: Lecturer | AQ100: Lecturer | AT100: UNIVERSITY OF NAIROBI | AU100: 0000-0001-6367-1010 | AV100: No | AW100: 42065 | AX100: 42310 | AY100: Yes | AZ100: 42248 | BA100: 43503 | BE100: A study of antioxidant, hypoglycemic and hypolipidemic activities of plants used in food by the Maasai community | BF100: 42947 | BG100: Yes | BH100: 43164 | BI100: Yes | BN100: In progress | BR100: 0 | BS100: 0 | BT100: 0 | BU100: 0 | BV100: 0 | BW100: 0 | BX100: 0 | BY100: No | BZ100: 0 | CE100: No | CH100: 2 | CI100: NF | CK100: SIDA/DAAD
...

Sheet Terminations
A1: No. | B1: Name | C1: Institution | D1: Gender | E1: Cohort | F1: Suspension | G1: Date of Termination | H1: Year | I1: Reason for Termination | J1: Detailed reason for termination
A2: 1 | B2: Stephen Pentz | C2: University of Witwatersrand | D2: Male | E2: 3 | G2: 2014 | H2: 2014 | I2: Lack of progress on milestone
A3: 2 | B3: Humphrey Phanuel Shao | C3: Ifakara Health Institute | D3: Male | E3: 3 | G3: 2016 | H3: 2016 | I3: Lack of progress on milestone
A4: 3 | B4: Peter Mwamba | C4: University of Nairobi | D4: Male | E4: 1 | F4: Yes | G4: 42583 | H4: 2016 | I4: Lack of progress on milestone
A5: 4 | B5: Gloria Omosa | C5: University of Nairobi | D5: Female | E5: 2 | F5: Aug 29 2014 | G5: October 2016 | H5: 2016 | I5: Failure to meet key milestone
A6: 5 | B6: Gad Rutayisire | C6: University of Rwanda | D6: Male | E6: 7 | F6: Nov 2 2017 | G6: 2017 | H6: 2017 | I6: Lack of progress on milestone
A7: 6 | B7: Gift Khangamwa | C7: University of Malawi | D7: Male | E7: 5 | F7: June 5 2017 | G7: 2017 | H7: 2017 | I7: Master Degree not recognised
A8: 7 | B8: Callen Onyambu | C8: University of Nairobi | D8: Female | E8: 5 | F8: June 5 2017 | G8: 2018 | H8: 2018 | I8: Lack of progress on milestone
A9: 8 | B9: Edwin Sang | C9: Moi University | D9: Male | E9: 6 | G9: 2018 | H9: 2018 | I9: Lack of progress on milestone
A10: 9 | B10: Hussein Masoud | C10: University of Dar es Salaam | D10: Male | E10: 5 | F10: yes | G10: 2018 | H10: 2018 | I10: Lack of progress on milestone
A11: 10 | B11: Teresa Kinyari | C11: University of Nairobi | D11: Female | E11: 1 | F11: Nov 18 2011 | G11: Not indicated | I11: Lack of progress on milestone
A12: 11 | B12: Jacqueline Mgumia | C12: University of Dar es Salaam | D12: Female | E12: 1 | F12: Feb 8 2012 | G12: Not indicated | I12: Lack of progress on milestone
A13: 12 | B13: Lackson Tembo | C13: University of Malawi | D13: Male | E13: 4 | G13: 43867 | H13: 2020 | I13: Lack of progress on milestone
A14: 13 | B14: Doris Kwesiga | C14: Makerere University | D14: Female | E14: 8 | G14: 43867 | H14: 2020 | I14: Inability to attend JAS 2 twice | J14: Unable to attend JAS 2 in South Africa due to her visa issues
A15: 14 | B15: Raymond Odokonyero | C15: Makerere University | D15: Male | E15: 5 | G15: 43930 | H15: 2020 | I15: Lack of progress on milestone
A16: 15 | B16: Justus Musasiah | C16: APHRC | D16: Male | E16: 7 | G16: 43930 | H16: 2020 | I16: Lack of progress on milestone | J16: Inability to continue participating in CARTA activities after moving institutions
A17: 16 | B17: Edna Wairimu Kamau | C17: University of Nairobi | D17: Female | E17: 7 | G17: 44214 | H17: 2021 | I17: Requested for termination | J17: She requested for termination after the secretariat followed up on her delay to meet milestones
A18: 17 | B18: Leo Masamba | C18: University of Malawi | D18: Male | E18: 8 | G18: 44400 | H18: 2021 | I18: Lack of progress on milestone | J18: Failure to register for PhD at an African partner institution
A19: 18 | B19: Florence Basiimwa Tuishemirirwe | C19: Makerere University | D19: Male | E19: 8 | G19: 44651 | H19: 2022 | I19: Failure to secure registration after being in the program for 3 years | J19: Cohort 8 fellow she was under long suspension up to December 31, 2021 to share her registration. She did not failed We have not received any evidence of registration despite having requested for it several times. .
A20: 19 | B20: Jane Wanjiru Macharia | C20: University of Nairobi | D20: Female | E20: 9 | G20: 44818 | H20: 2022 | I20: Requested for termination | J20: Jane Macharia had made significant progress (had requested for research funds) but requested for leave of absence in July 2021 citing personal challenges with her supervisor. In July 2022 we initiated the process for her to resume her fellowship, however, she indicated that she still had challenges with her supervisor. Efforts by the secretariat and the University of Nairobi focal person to mediate between her and her supervisor have not borne fruit, and she has instead opted to terminate her fellowship
A21: 20 | B21: Joselyn Atahuirwe | C21: Makerere University | D21: Female | E21: 9 | G21: 44818 | H21: 2022 | I21: Lack of progress on milestone | J21: Joselyn Atuhairwe joined CARTA in 2019 with cohort 9 but has been slow in making progress throughout. She requested for one-year leave of absence due to health challenges right after JAS1. After resumption of her fellowship she has consistently been behind her peers in cohort 10 even in completing ESE:O assignments. As of now, she has not obtained university registration nor presented her protocol. She was invited to attend the face-to-face session of JAS 2 but declined despite all efforts from the focal person and the secretariat to accommodate her needs.
A22: 21 | B22: Duncan Nyukuri | C22: Makerere University | D22: Male | E22: 10 | G22: 45107 | H22: 2023 | I22: Lack of progress on milestone | J22: Duncan failed to attend part 2 of JAS 2 in 2022 JAS 3 in 2023 and did not communicate or respond to the secretariat when they reached out to him
A23: 22 | B23: Siphesihle Mtshali | C23: University of Witwatersrand | E23: 2 | G23: 45741 | H23: 2025 | I23: Has been nonresponsive to our communication. The last time she registered was 2016 and her account has been suspended
A24: 23 | B24: Simbaharshe Takuva | C24: University of Witwatersrand | E24: 2 | G24: 45741 | H24: 2025 | I24: Has been nonresponsive to our communication. Her account in the Wits system is no longer act
A25: 24 | B25: Nicolette Prea Naidoo | C25: University of Witwatersrand | E25: 3 | G25: 45741 | H25: 2025 | I25: Has been nonresponsive to our communication. The last time she registered was 2018 and her account has been suspended
A26: 25 | B26: Nomathemba Chiwoneso Chandiwana | C26: University of Witwatersrand | E26: 5 | G26: 45741 | H26: 2025 | I26: Has been nonresponsive to our communication. The last time she registered was 2019 and her account has been suspended
A27: 26 | B27: Pierre Celestin Munezero | C27: University of Rwanda | D27: Male | E27: 11 | G27: 13/11/2025 | H27: 2025 | I27: Registered at a non Africa university | J27: Registered for their PhD at the University of Guelph, a non African University

Sheet Promotions
E2: Date of completion(Defended/Graduated) | F2: (Multiple Items)
E4: Count of Unique ID | F4: Gender | G4: Current PhD Status ( Completed/Defended/In Progress)
F5: Woman | G5: Woman Total | H5: Grand Total
E6: Institution of employment at registration | F6: Completed
E7: Moi University | F7: 1 | G7: 1 | H7: 1
E8: Obafemi Awolowo University | F8: 1 | G8: 1 | H8: 1
E9: University of Ibadan | F9: 1 | G9: 1 | H9: 1
E10: University of Nairobi | F10: 1 | G10: 1 | H10: 1
E11: University of the Witwatersrand | F11: 2 | G11: 2 | H11: 2
E12: Grand Total | F12: 6 | G12: 6 | H12: 6
E24: Current PhD Status ( Completed/Defended/In Progress) | F24: (All)
E26: Count of S.No. | F26: Gender
E27: Institution of employment at registration | F27: Man | G27: Woman | H27: Grand Total
E28: AGINCOURT | F28: 3 | H28: 3
E29: APHRC | F29: 5 | G29: 1 | H29: 6
E30: Ifakara Health Institute | F30: 4 | G30: 6 | H30: 10
E31: Makerere University | F31: 17 | G31: 14 | H31: 31
E32: Moi University | F32: 5 | G32: 17 | H32: 22
E33: Obafemi Awolowo University | F33: 15 | G33: 18 | H33: 33
E34: University of Dar es Salaam | F34: 3 | G34: 3 | H34: 6
E35: University of Ibadan | F35: 20 | G35: 23 | H35: 43
E36: University of Nairobi | F36: 7 | G36: 24 | H36: 31
E37: University of Rwanda | F37: 19 | G37: 12 | H37: 31
E38: University of the Witwatersrand | F38: 9 | G38: 23 | H38: 32
E39: Somali National University | F39: 1 | G39: 1 | H39: 2
E40: University of Malawi and Associates | F40: 22 | G40: 15 | H40: 37
E41: Grand Total | F41: 130 | G41: 157 | H41: 287
E46: Promotion event | F46: (All)
E48: Count of S.No. | F48: Gender
E49: Institution of employment at registration | F49: Man | G49: Woman | H49: Grand Total
E50: AGINCOURT | F50: 2 | H50: 2
E51: APHRC | F51: 4 | G51: 1 | H51: 5
E52: Ifakara Health Institute | F52: 3 | G52: 6 | H52: 9
E53: Makerere University | F53: 16 | G53: 11 | H53: 27
E54: Moi University | F54: 5 | G54: 16 | H54: 21
E55: Obafemi Awolowo University | F55: 15 | G55: 18 | H55: 33
E56: Somali National University | F56: 1 | G56: 1 | H56: 2
E57: University of Dar es Salaam | F57: 3 | G57: 3 | H57: 6
E58: University of Ibadan | F58: 16 | G58: 23 | H58: 39
E59: University of Nairobi | F59: 7 | G59: 23 | H59: 30
E60: University of Rwanda | F60: 16 | G60: 11 | H60: 27
E61: University of the Witwatersrand | F61: 9 | G61: 22 | H61: 31
E62: University of Malawi and Associates | F62: 21 | G62: 12 | H62: 33
E63: Grand Total | F63: 118 | G63: 147 | H63: 265

Sheet Sheet1
A1: Date of completion(Defended/Graduated) | B1: (All)
A3: Current PhD Status ( Completed/Defended/In Progress) | B3: Count of S.No.
A4: Completed | B4: 197
A5: In progress | B5: 42
A6: Terminated | B6: 26
A7: Grand Total | B7: 265
A14: Date of completion(Defended/Graduated) | B14: (All)
A15: Cohort | B15: (All)
A17: Nationality | B17: Count of S.No.
A18: Kenya | B18: 58
A19: Malawi | B19: 39
A20: Nigeria | B20: 78
A21: Rwanda | B21: 31
A22: Senegal | B22: 1
A23: Somalia | B23: 2
A24: South Africa | B24: 28
A25: Tanzania | B25: 16
A26: Uganda | B26: 31
A27: Zimbabwe | B27: 3
A28: Grand Total | B28: 287
